Workbook

Sheet Portada

Sheet Atlas y nueva venta
B2: Mes | C2: Alta sin facturar | D2: Cliente nuevo (ha facturado) | E2: Cliente (3 facturas o +) | F2: Total general
B3: Enero | C3: =Datos!AH6 -> 55 | D3: =Datos!AJ6 -> 35 | E3: =Datos!AI6 -> 42 | F3: =SUM(C3:E3) -> 132
C4: - | D4: =Datos!AJ21 -> 239243.04 | E4: =Datos!AI21 -> 4216487.5 | F4: =SUM(C4:E4) -> 4455730.5
B5: Febrero | C5: =Datos!AH7 -> 28 | D5: =Datos!AJ7 -> 23 | E5: =Datos!AI7 -> 28 | F5: =SUM(C5:E5) -> 79
C6: - | D6: =Datos!AJ22 -> 139022.52 | E6: =Datos!AI22 -> 923884.32 | F6: =SUM(C6:E6) -> 1062906.8
B7: Marzo | C7: =Datos!AH8 -> 33 | D7: =Datos!AJ8 -> 24 | E7: =Datos!AI8 -> 37 | F7: =SUM(C7:E7) -> 94
C8: - | D8: =Datos!AJ23 -> 98967.72 | E8: =Datos!AI23 -> 964667.6 | F8: =SUM(C8:E8) -> 1063635.3
B9: Abril | C9: =Datos!AH9 -> 18 | D9: =Datos!AJ9 -> 22 | E9: =Datos!AI9 -> 36 | F9: =SUM(C9:E9) -> 76
C10: - | D10: =Datos!AJ24 -> 43425.609 | E10: =Datos!AI24 -> 1000965.7 | F10: =SUM(C10:E10) -> 1044391.3
B11: Mayo | C11: =Datos!AH10 -> 20 | D11: =Datos!AJ10 -> 26 | E11: =Datos!AI10 -> 31 | F11: =SUM(C11:E11) -> 77
C12: - | D12: =Datos!AJ25 -> 285948.12 | E12: =Datos!AI25 -> 523948.8 | F12: =SUM(C12:E12) -> 809896.92
B13: Junio | C13: =Datos!AH11 -> 27 | D13: =Datos!AJ11 -> 50 | E13: =Datos!AI11 -> 24 | F13: =SUM(C13:E13) -> 101
C14: - | D14: =Datos!AJ26 -> 231706.52 | E14: =Datos!AI26 -> 422584.52 | F14: =SUM(C14:E14) -> 654291.04
B15: Julio | C15: =Datos!AH12 -> 36 | D15: =Datos!AJ12 -> 56 | E15: =Datos!AI12 -> 0 | F15: =SUM(C15:E15) -> 92
C16: - | D16: =Datos!AJ27 -> 251399.84 | E16: =Datos!AI27 -> 0 | F16: =SUM(C16:E16) -> 251399.84 | R16: Han pagado | S16: Enero | T16: Febrero | U16: Marzo | V16: Abril | W16: Mayo | X16: Junio | Y16: Julio | Z16: Total
B17: Agosto | C17: =Datos!AH13 -> 62 | D17: =Datos!AJ13 -> 13 | E17: =Datos!AI13 -> 0 | F17: =SUM(C17:E17) -> 75
C18: - | D18: =Datos!AJ28 -> 24922.6 | E18: =Datos!AI28 -> 0 | F18: =SUM(C18:E18) -> 24922.6
B19: Total altas | C19: =SUM(C3,C5,C7,C9,C11,C13,C15,C17) -> 279 | D19: =SUM(D3,D5,D7,D9,D11,D13,D15,D17) -> 249 | E19: =SUM(E3,E5,E7,E9,E11,E13,E15,E17) -> 198 | F19: =SUM(F3,F5,F7,F9,F11,F13,F15,F17) -> 726 | R19: Cliente nuevo | S19: =IFERROR(Datos!AH36&" - "&TEXT(Datos!AH36/(Datos!AH37+Datos!AH36),"0.0%"),"") -> 13 - 19.7% | T19: =IFERROR(Datos!AI36&" - "&TEXT(Datos!AI36/(Datos!AI37+Datos!AI36),"0.0%"),"") -> 14 - 34.1% | U19: =IFERROR(Datos!AJ36&" - "&TEXT(Datos!AJ36/(Datos!AJ37+Datos!AJ36),"0.0%"),"") -> 21 - 38.9% | V19: =IFERROR(Datos!AK36&" - "&TEXT(Datos!AK36/(Datos!AK37+Datos!AK36),"0.0%"),"") -> 14 - 35.9% | W19: =IFERROR(Datos!AL36&" - "&TEXT(Datos!AL36/(Datos!AL37+Datos!AL36),"0.0%"),"") -> 11 - 52.4% | X19: =IFERROR(Datos!AM36&" - "&TEXT(Datos!AM36/(Datos!AM37+Datos!AM36),"0.0%"),"") -> 14 - 100.0% | Z19: =Datos!AN36 -> 87
B20: % | C20: =C19/F19 -> 0.38429752 | D20: =D19/F19 -> 0.34297521 | E20: =E19/F19 -> 0.27272727 | R20: Cliente | S20: =IFERROR(Datos!AH37&" - "&TEXT(Datos!AH37/(Datos!AH37+Datos!AH36),"0.0%"),"") -> 53 - 80.3% | T20: =IFERROR(Datos!AI37&" - "&TEXT(Datos!AI37/(Datos!AI37+Datos!AI36),"0.0%"),"") -> 27 - 65.9% | U20: =IFERROR(Datos!AJ37&" - "&TEXT(Datos!AJ37/(Datos!AJ37+Datos!AJ36),"0.0%"),"") -> 33 - 61.1% | V20: =IFERROR(Datos!AK37&" - "&TEXT(Datos!AK37/(Datos!AK37+Datos!AK36),"0.0%"),"") -> 25 - 64.1% | W20: =IFERROR(Datos!AL37&" - "&TEXT(Datos!AL37/(Datos!AL37+Datos!AL36),"0.0%"),"") -> 10 - 47.6% | X20: =IFERROR(Datos!AM37&" - "&TEXT(Datos!AM37/(Datos!AM37+Datos!AM36),"0.0%"),"") -> 0 - 0.0% | Z20: =Datos!AN37 -> 148
B21: Total venta | C21: =SUM(C4,C6,C8,C10,C12,C14,C16,C18) -> 0 | D21: =SUM(D4,D6,D8,D10,D12,D14,D16,D18) -> 1314636 | E21: =SUM(E4,E6,E8,E10,E12,E14,E16,E18) -> 8052538.5 | F21: =SUM(F4,F6,F8,F10,F12,F14,F16,F18) -> 9367174.4 | R21: Total | S21: =IFERROR(Datos!AH38,"0.0%") -> 13 | T21: =IFERROR(Datos!AI38,"0.0%") -> 13 | U21: =IFERROR(Datos!AJ38,"0.0%") -> 8 | V21: =IFERROR(Datos!AK38,"0.0%") -> 17 | W21: =IFERROR(Datos!AL38,"0.0%") -> 29 | X21: =IFERROR(Datos!AM38,"0.0%") -> 49 | Y21: =IFERROR(Datos!AN38,"0.0%") -> 129 | Z21: =Datos!AN38 -> 129
R23: Han pagado | S23: Enero | T23: Febrero | U23: Marzo | V23: Abril | W23: Mayo | X23: Junio | Y23: Julio | Z23: Total
R24: Cliente nuevo | S24: =Datos!AH46 -> 0 | T24: =Datos!AI46 -> 0 | U24: =Datos!AJ46 -> 0 | V24: =Datos!AK46 -> 0 | W24: =Datos!AL46 -> 0 | X24: =Datos!AM46 -> 0 | Z24: =SUM(S24:X24) -> 0
R25: Cliente | S25: =Datos!AH47 -> 0 | T25: =Datos!AI47 -> 0 | U25: =Datos!AJ47 -> 0 | V25: =Datos!AK47 -> 0 | W25: =Datos!AL47 -> 0 | X25: =Datos!AM47 -> 0 | Z25: =SUM(S25:X25) -> 0
R26: Total | S26: =SUM(S24:S25) -> 0 | T26: =SUM(T24:T25) -> 0 | U26: =SUM(U24:U25) -> 0 | V26: =SUM(V24:V25) -> 0 | W26: =SUM(W24:W25) -> 0 | X26: =SUM(X24:X25) -> 0 | Z26: =SUM(S26:X26) -> 0
R28: Sin pago | S28: Enero | T28: Febrero | U28: Marzo | V28: Abril | W28: Mayo | X28: Junio | Y28: Julio | Z28: Total
R29: Cliente | S29: =IF(Datos!AH56=0,"",IFERROR(Datos!AH56&" - "&TEXT(Datos!AH56/(Datos!AH56+Datos!AH36),"0.0%"),"")) | T29: =IF(Datos!AI56=0,"",IFERROR(Datos!AI56&" - "&TEXT(Datos!AI56/(Datos!AI56+Datos!AI36),"0.0%"),"")) | U29: =IF(Datos!AJ56=0,"",IFERROR(Datos!AJ56&" - "&TEXT(Datos!AJ56/(Datos!AJ56+Datos!AJ36),"0.0%"),"")) | V29: =IF(Datos!AK56=0,"",IFERROR(Datos!AK56&" - "&TEXT(Datos!AK56/(Datos!AK56+Datos!AK36),"0.0%"),"")) | W29: =IF(Datos!AL56=0,"",IFERROR(Datos!AL56&" - "&TEXT(Datos!AL56/(Datos!AL56+Datos!AL36),"0.0%"),"")) | X29: =IF(Datos!AM56=0,"",IFERROR(Datos!AM56&" - "&TEXT(Datos!AM56/(Datos!AM56+Datos!AM36),"0.0%"),"")) | Z29: =Datos!AN56 -> 0
R30: Cliente nuevo | S30: =IF(Datos!AH57=0,"",IFERROR(Datos!AH57&" - "&TEXT(Datos!AH57/(Datos!AH57+Datos!AH37),"0.0%"),"")) | T30: =IF(Datos!AI57=0,"",IFERROR(Datos!AI57&" - "&TEXT(Datos!AI57/(Datos!AI57+Datos!AI37),"0.0%"),"")) | U30: =IF(Datos!AJ57=0,"",IFERROR(Datos!AJ57&" - "&TEXT(Datos!AJ57/(Datos!AJ57+Datos!AJ37),"0.0%"),"")) | V30: =IF(Datos!AK57=0,"",IFERROR(Datos!AK57&" - "&TEXT(Datos!AK57/(Datos!AK57+Datos!AK37),"0.0%"),"")) | W30: =IF(Datos!AL57=0,"",IFERROR(Datos!AL57&" - "&TEXT(Datos!AL57/(Datos!AL57+Datos!AL37),"0.0%"),"")) | X30: =IF(Datos!AM57=0,"",IFERROR(Datos!AM57&" - "&TEXT(Datos!AM57/(Datos!AM57+Datos!AM37),"0.0%"),"")) | Y30: =IF(Datos!AN57=0,"",IFERROR(Datos!AN57&" - "&TEXT(Datos!AN57/(Datos!AN57+Datos!AN37),"0.0%"),"")) | Z30: =Datos!AN57 -> 0
R31: Total general | S31: =IF(Datos!AH58=0,"",IFERROR(Datos!AH58&" - "&TEXT(Datos!AH58/(Datos!AH58+Datos!AH38),"0.0%"),"")) | T31: =IF(Datos!AI58=0,"",IFERROR(Datos!AI58&" - "&TEXT(Datos!AI58/(Datos!AI58+Datos!AI38),"0.0%"),"")) | U31: =IF(Datos!AJ58=0,"",IFERROR(Datos!AJ58&" - "&TEXT(Datos!AJ58/(Datos!AJ58+Datos!AJ38),"0.0%"),"")) | V31: =IF(Datos!AK58=0,"",IFERROR(Datos!AK58&" - "&TEXT(Datos!AK58/(Datos!AK58+Datos!AK38),"0.0%"),"")) | W31: =IF(Datos!AL58=0,"",IFERROR(Datos!AL58&" - "&TEXT(Datos!AL58/(Datos!AL58+Datos!AL38),"0.0%"),"")) | X31: =IF(Datos!AM58=0,"",IFERROR(Datos!AM58&" - "&TEXT(Datos!AM58/(Datos!AM58+Datos!AM38),"0.0%"),"")) | Y31: =IF(Datos!AN58=0,"",IFERROR(Datos!AN58&" - "&TEXT(Datos!AN58/(Datos!AN58+Datos!AN38),"0.0%"),"")) | Z31: =Datos!AN58 -> 0
R33: Sin pago | S33: Enero | T33: Febrero | U33: Marzo | V33: Abril | W33: Mayo | X33: Junio | Y33: Julio | Z33: Total
R34: Cliente | S34: =Datos!AH65 -> 0 | T34: =Datos!AI65 -> 0 | U34: =Datos!AJ65 -> 0 | V34: =Datos!AK65 -> 0 | W34: =Datos!AL65 -> 0 | X34: =Datos!AM65 -> 0 | Z34: =SUM(S34:X34) -> 0
R35: Cliente nuevo | S35: =Datos!AH66 -> 0 | T35: =Datos!AI66 -> 0 | U35: =Datos!AJ66 -> 0 | V35: =Datos!AK66 -> 0 | W35: =Datos!AL66 -> 0 | X35: =Datos!AM66 -> 0 | Z35: =SUM(S35:X35) -> 0
R36: Total general | S36: =SUM(S34:S35) -> 0 | T36: =SUM(T34:T35) -> 0 | U36: =SUM(U34:U35) -> 0 | V36: =SUM(V34:V35) -> 0 | W36: =SUM(W34:W35) -> 0 | X36: =SUM(X34:X35) -> 0 | Z36: =SUM(S36:X36) -> 0
S41: .

Sheet Altas x ejecutivo
R1: Ejecutivo | S1: (Varios elementos)
H2: Cuenta de Categoría | I2: Categoría
B3: Ejecutivo | C3: Alta sin facturar (%) | D3: Cliente nuevo (%) | E3: Cliente (%) | G3: Región | H3: Ejecutivo | I3: Alta sin facturar | J3: Cliente nuevo | K3: Cliente | L3: Total altas | M3: =IF(L3="",K3,L3) -> Total altas | N3: Facturado | O3: Límite | S3: Altas | W3: % Altas
B4: =IF(H4="","",H4) -> Yareli Flores | C4: =IF(H4="","",I4/IF(M4="",K4,M4)) -> 0.5862069 | D4: =IF(H4="","",J4/IF(M4="",K4,M4)) -> 0.15517241 | E4: =IF(H4="","",K4/IF(M4="",K4,M4)) -> 0.25862069 | G4: =IFERROR(VLOOKUP(H4,Datos!C:D,2,0),"") -> Centro | H4: Yareli Flores | I4: 34 | J4: 9 | K4: 15 | L4: 58 | M4: =IF(H4="","",IF(L4="",K4,L4)) -> 58 | N4: =_xlfn.XLOOKUP(H4,Datos!$AT$3:$AT$30,Datos!$AX$3:$AX$30,"") -> 423867.48 | O4: =$N$4 -> 423867.48 | P4: =IF(AND(N4>=LARGE($N$4:$N$31,5),M4>=LARGE($M$4:$M$31,5)),1,0) -> 1 | R4: Región | S4: sin facturar | T4: Cliente nuevo | U4: Cliente | V4: Suma | W4: sin facturar
B5: =IF(H5="","",H5) -> Ricardo Vidal | C5: =IF(H5="","",I5/IF(M5="",K5,M5)) -> 0.27777778 | D5: =IF(H5="","",J5/IF(M5="",K5,M5)) -> 0.5 | E5: =IF(H5="","",K5/IF(M5="",K5,M5)) -> 0.22222222 | G5: =IFERROR(VLOOKUP(H5,Datos!C:D,2,0),"") -> Magallanes | H5: Ricardo Vidal | I5: 15 | J5: 27 | K5: 12 | L5: 54 | M5: =IF(H5="","",IF(L5="",K5,L5)) -> 54 | N5: =_xlfn.XLOOKUP(H5,Datos!$AT$3:$AT$30,Datos!$AX$3:$AX$30,"") -> 256792.68 | O5: =$N$4 -> 423867.48 | P5: =IF(AND(N5>=LARGE($N$4:$N$31,5),M5>=LARGE($M$4:$M$31,5)),1,0) -> 0 | R5: Norte | S5: 68 | T5: 45 | U5: 65 | V5: 178 | W5: =GETPIVOTDATA("Categoría",$S$5,"Región","NORTE","Categoría","Alta sin facturar")/GETPIVOTDATA("Categoría",$V$5,"Región","NORTE") -> 0.38202247
B6: =IF(H6="","",H6) -> Marcos López | C6: =IF(H6="","",I6/IF(M6="",K6,M6)) -> 0.20930233 | D6: =IF(H6="","",J6/IF(M6="",K6,M6)) -> 0.79069767 | E6: =IF(H6="","",K6/IF(M6="",K6,M6)) -> 0 | G6: =IFERROR(VLOOKUP(H6,Datos!C:D,2,0),"") -> Sur | H6: Marcos López | I6: 9 | J6: 34 | L6: 43 | M6: =IF(H6="","",IF(L6="",K6,L6)) -> 43 | N6: =_xlfn.XLOOKUP(H6,Datos!$AT$3:$AT$30,Datos!$AX$3:$AX$30,"") -> 312603.76 | O6: =$N$4 -> 423867.48 | P6: =IF(AND(N6>=LARGE($N$4:$N$31,5),M6>=LARGE($M$4:$M$31,5)),1,0) -> 0 | R6: Centro | S6: 141 | T6: 75 | U6: 79 | V6: 295 | W6: =GETPIVOTDATA("Categoría",$R$3,"Región","CENTRO","Categoría","Alta sin facturar")/GETPIVOTDATA("Categoría",$R$3,"Región","CENTRO") -> 0.4779661
B7: =IF(H7="","",H7) -> Alfredo Almaráz | C7: =IF(H7="","",I7/IF(M7="",K7,M7)) -> 0.25581395 | D7: =IF(H7="","",J7/IF(M7="",K7,M7)) -> 0.41860465 | E7: =IF(H7="","",K7/IF(M7="",K7,M7)) -> 0.3255814 | G7: =IFERROR(VLOOKUP(H7,Datos!C:D,2,0),"") -> Magallanes | H7: Alfredo Almaráz | I7: 11 | J7: 18 | K7: 14 | L7: 43 | M7: =IF(H7="","",IF(L7="",K7,L7)) -> 43 | N7: =_xlfn.XLOOKUP(H7,Datos!$AT$3:$AT$30,Datos!$AX$3:$AX$30,"") -> 461678.84 | O7: =$N$4 -> 423867.48 | P7: =IF(AND(N7>=LARGE($N$4:$N$31,5),M7>=LARGE($M$4:$M$31,5)),1,0) -> 1 | R7: Sur | S7: 25 | T7: 66 | U7: 28 | V7: 119 | W7: =GETPIVOTDATA("Categoría",$R$3,"Región","SUR","Categoría","Alta sin facturar")/GETPIVOTDATA("Categoría",$R$3,"Región","SUR") -> 0.21008403
B8: =IF(H8="","",H8) -> Miguel Romero | C8: =IF(H8="","",I8/IF(M8="",K8,M8)) -> 0.45238095 | D8: =IF(H8="","",J8/IF(M8="",K8,M8)) -> 0.38095238 | E8: =IF(H8="","",K8/IF(M8="",K8,M8)) -> 0.16666667 | G8: =IFERROR(VLOOKUP(H8,Datos!C:D,2,0),"") -> Centro | H8: Miguel Romero | I8: 19 | J8: 16 | K8: 7 | L8: 42 | M8: =IF(H8="","",IF(L8="",K8,L8)) -> 42 | N8: =_xlfn.XLOOKUP(H8,Datos!$AT$3:$AT$30,Datos!$AX$3:$AX$30,"") | O8: =$N$4 -> 423867.48 | P8: =IF(AND(N8>=LARGE($N$4:$N$31,5),M8>=LARGE($M$4:$M$31,5)),1,0) -> 1 | R8: Magallanes | S8: 36 | T8: 63 | U8: 26 | V8: 125 | W8: =GETPIVOTDATA("Categoría",$R$3,"Región","MAGALLANES","Categoría","Alta sin facturar")/GETPIVOTDATA("Categoría",$R$3,"Región","MAGALLANES") -> 0.288
B9: =IF(H9="","",H9) -> Genaro Castro | C9: =IF(H9="","",I9/IF(M9="",K9,M9)) -> 0.26190476 | D9: =IF(H9="","",J9/IF(M9="",K9,M9)) -> 0.35714286 | E9: =IF(H9="","",K9/IF(M9="",K9,M9)) -> 0.38095238 | G9: =IFERROR(VLOOKUP(H9,Datos!C:D,2,0),"") -> Sur | H9: Genaro Castro | I9: 11 | J9: 15 | K9: 16 | L9: 42 | M9: =IF(H9="","",IF(L9="",K9,L9)) -> 42 | N9: =_xlfn.XLOOKUP(H9,Datos!$AT$3:$AT$30,Datos!$AX$3:$AX$30,"") -> 381845.32 | O9: =$N$4 -> 423867.48 | P9: =IF(AND(N9>=LARGE($N$4:$N$31,5),M9>=LARGE($M$4:$M$31,5)),1,0) -> 0
B10: =IF(H10="","",H10) -> Christian Castellanos | C10: =IF(H10="","",I10/IF(M10="",K10,M10)) -> 0.525 | D10: =IF(H10="","",J10/IF(M10="",K10,M10)) -> 0.1 | E10: =IF(H10="","",K10/IF(M10="",K10,M10)) -> 0.375 | G10: =IFERROR(VLOOKUP(H10,Datos!C:D,2,0),"") -> Norte | H10: Christian Castellanos | I10: 21 | J10: 4 | K10: 15 | L10: 40 | M10: =IF(H10="","",IF(L10="",K10,L10)) -> 40 | N10: =_xlfn.XLOOKUP(H10,Datos!$AT$3:$AT$30,Datos!$AX$3:$AX$30,"") -> 836155.84 | O10: =$N$4 -> 423867.48 | P10: =IF(AND(N10>=LARGE($N$4:$N$31,5),M10>=LARGE($M$4:$M$31,5)),1,0) -> 0 | R10: Mejor facturación
B11: =IF(H11="","",H11) -> Rubí Rodríguez | C11: =IF(H11="","",I11/IF(M11="",K11,M11)) -> 0.3030303 | D11: =IF(H11="","",J11/IF(M11="",K11,M11)) -> 0.36363636 | E11: =IF(H11="","",K11/IF(M11="",K11,M11)) -> 0.33333333 | G11: =IFERROR(VLOOKUP(H11,Datos!C:D,2,0),"") -> Centro | H11: Rubí Rodríguez | I11: 10 | J11: 12 | K11: 11 | L11: 33 | M11: =IF(H11="","",IF(L11="",K11,L11)) -> 33 | N11: =_xlfn.XLOOKUP(H11,Datos!$AT$3:$AT$30,Datos!$AX$3:$AX$30,"") -> 219351.36 | O11: =$N$4 -> 423867.48 | P11: =IF(AND(N11>=LARGE($N$4:$N$31,5),M11>=LARGE($M$4:$M$31,5)),1,0) -> 0 | R11: Más altas
B12: =IF(H12="","",H12) -> Dolores Jiménez | C12: =IF(H12="","",I12/IF(M12="",K12,M12)) -> 0.1875 | D12: =IF(H12="","",J12/IF(M12="",K12,M12)) -> 0.21875 | E12: =IF(H12="","",K12/IF(M12="",K12,M12)) -> 0.59375 | G12: =IFERROR(VLOOKUP(H12,Datos!C:D,2,0),"") -> Norte | H12: Dolores Jiménez | I12: 6 | J12: 7 | K12: 19 | L12: 32 | M12: =IF(H12="","",IF(L12="",K12,L12)) -> 32 | N12: =_xlfn.XLOOKUP(H12,Datos!$AT$3:$AT$30,Datos!$AX$3:$AX$30,"") -> 336259.64 | O12: =$N$4 -> 423867.48 | P12: =IF(AND(N12>=LARGE($N$4:$N$31,5),M12>=LARGE($M$4:$M$31,5)),1,0) -> 0
B13: =IF(H13="","",H13) -> Iván Luna | C13: =IF(H13="","",I13/IF(M13="",K13,M13)) -> 0.41935484 | D13: =IF(H13="","",J13/IF(M13="",K13,M13)) -> 0.32258065 | E13: =IF(H13="","",K13/IF(M13="",K13,M13)) -> 0.25806452 | G13: =IFERROR(VLOOKUP(H13,Datos!C:D,2,0),"") -> Norte | H13: Iván Luna | I13: 13 | J13: 10 | K13: 8 | L13: 31 | M13: =IF(H13="","",IF(L13="",K13,L13)) -> 31 | N13: =_xlfn.XLOOKUP(H13,Datos!$AT$3:$AT$30,Datos!$AX$3:$AX$30,"") -> 2948272.2 | O13: =$N$4 -> 423867.48 | P13: =IF(AND(N13>=LARGE($N$4:$N$31,5),M13>=LARGE($M$4:$M$31,5)),1,0) -> 0
B14: =IF(H14="","",H14) -> Oscar Moreno | C14: =IF(H14="","",I14/IF(M14="",K14,M14)) -> 0.35714286 | D14: =IF(H14="","",J14/IF(M14="",K14,M14)) -> 0.64285714 | E14: =IF(H14="","",K14/IF(M14="",K14,M14)) -> 0 | G14: =IFERROR(VLOOKUP(H14,Datos!C:D,2,0),"") -> Magallanes | H14: Oscar Moreno | I14: 10 | J14: 18 | L14: 28 | M14: =IF(H14="","",IF(L14="",K14,L14)) -> 28 | N14: =_xlfn.XLOOKUP(H14,Datos!$AT$3:$AT$30,Datos!$AX$3:$AX$30,"") -> 99958.36 | O14: =$N$4 -> 423867.48 | P14: =IF(AND(N14>=LARGE($N$4:$N$31,5),M14>=LARGE($M$4:$M$31,5)),1,0) -> 0
B15: =IF(H15="","",H15) -> Diana Tejadilla | C15: =IF(H15="","",I15/IF(M15="",K15,M15)) -> 0.46428571 | D15: =IF(H15="","",J15/IF(M15="",K15,M15)) -> 0.28571429 | E15: =IF(H15="","",K15/IF(M15="",K15,M15)) -> 0.25 | G15: =IFERROR(VLOOKUP(H15,Datos!C:D,2,0),"") -> Centro | H15: Diana Tejadilla | I15: 13 | J15: 8 | K15: 7 | L15: 28 | M15: =IF(H15="","",IF(L15="",K15,L15)) -> 28 | N15: =_xlfn.XLOOKUP(H15,Datos!$AT$3:$AT$30,Datos!$AX$3:$AX$30,"") -> 118622.76 | O15: =$N$4 -> 423867.48 | P15: =IF(AND(N15>=LARGE($N$4:$N$31,5),M15>=LARGE($M$4:$M$31,5)),1,0) -> 0
B16: =IF(H16="","",H16) -> Yuritzi Alejo | C16: =IF(H16="","",I16/IF(M16="",K16,M16)) -> 0.44 | D16: =IF(H16="","",J16/IF(M16="",K16,M16)) -> 0.16 | E16: =IF(H16="","",K16/IF(M16="",K16,M16)) -> 0.4 | G16: =IFERROR(VLOOKUP(H16,Datos!C:D,2,0),"") -> Centro | H16: Yuritzi Alejo | I16: 11 | J16: 4 | K16: 10 | L16: 25 | M16: =IF(H16="","",IF(L16="",K16,L16)) -> 25 | N16: =_xlfn.XLOOKUP(H16,Datos!$AT$3:$AT$30,Datos!$AX$3:$AX$30,"") -> 772279.86 | O16: =$N$4 -> 423867.48 | P16: =IF(AND(N16>=LARGE($N$4:$N$31,5),M16>=LARGE($M$4:$M$31,5)),1,0) -> 0
B17: =IF(H17="","",H17) -> Leonard Lule | C17: =IF(H17="","",I17/IF(M17="",K17,M17)) -> 0.125 | D17: =IF(H17="","",J17/IF(M17="",K17,M17)) -> 0.375 | E17: =IF(H17="","",K17/IF(M17="",K17,M17)) -> 0.5 | G17: =IFERROR(VLOOKUP(H17,Datos!C:D,2,0),"") -> Sur | H17: Leonard Lule | I17: 3 | J17: 9 | K17: 12 | L17: 24 | M17: =IF(H17="","",IF(L17="",K17,L17)) -> 24 | N17: =_xlfn.XLOOKUP(H17,Datos!$AT$3:$AT$30,Datos!$AX$3:$AX$30,"") | O17: =$N$4 -> 423867.48 | P17: =IF(AND(N17>=LARGE($N$4:$N$31,5),M17>=LARGE($M$4:$M$31,5)),1,0) -> 0
B18: =IF(H18="","",H18) -> Yuriana Argüello | C18: =IF(H18="","",I18/IF(M18="",K18,M18)) -> 0.69565217 | D18: =IF(H18="","",J18/IF(M18="",K18,M18)) -> 0.26086957 | E18: =IF(H18="","",K18/IF(M18="",K18,M18)) -> 0.043478261 | G18: =IFERROR(VLOOKUP(H18,Datos!C:D,2,0),"") -> Centro | H18: Yuriana Argüello | I18: 16 | J18: 6 | K18: 1 | L18: 23 | M18: =IF(H18="","",IF(L18="",K18,L18)) -> 23 | N18: =_xlfn.XLOOKUP(H18,Datos!$AT$3:$AT$30,Datos!$AX$3:$AX$30,"") -> 319335.24 | O18: =$N$4 -> 423867.48 | P18: =IF(AND(N18>=LARGE($N$4:$N$31,5),M18>=LARGE($M$4:$M$31,5)),1,0) -> 0
B19: =IF(H19="","",H19) -> Blanca Montoya | C19: =IF(H19="","",I19/IF(M19="",K19,M19)) -> 0.80952381 | D19: =IF(H19="","",J19/IF(M19="",K19,M19)) -> 0.095238095 | E19: =IF(H19="","",K19/IF(M19="",K19,M19)) -> 0.095238095 | G19: =IFERROR(VLOOKUP(H19,Datos!C:D,2,0),"") -> Centro | H19: Blanca Montoya | I19: 17 | J19: 2 | K19: 2 | L19: 21 | M19: =IF(H19="","",IF(L19="",K19,L19)) -> 21 | N19: =_xlfn.XLOOKUP(H19,Datos!$AT$3:$AT$30,Datos!$AX$3:$AX$30,"") -> 84231.08 | O19: =$N$4 -> 423867.48 | P19: =IF(AND(N19>=LARGE($N$4:$N$31,5),M19>=LARGE($M$4:$M$31,5)),1,0) -> 0
B20: =IF(H20="","",H20) -> Sandra Escoto | C20: =IF(H20="","",I20/IF(M20="",K20,M20)) -> 0.35 | D20: =IF(H20="","",J20/IF(M20="",K20,M20)) -> 0.2 | E20: =IF(H20="","",K20/IF(M20="",K20,M20)) -> 0.45 | G20: =IFERROR(VLOOKUP(H20,Datos!C:D,2,0),"") -> Centro | H20: Sandra Escoto | I20: 7 | J20: 4 | K20: 9 | L20: 20 | M20: =IF(H20="","",IF(L20="",K20,L20)) -> 20 | N20: =_xlfn.XLOOKUP(H20,Datos!$AT$3:$AT$30,Datos!$AX$3:$AX$30,"") -> 218030.12 | O20: =$N$4 -> 423867.48 | P20: =IF(AND(N20>=LARGE($N$4:$N$31,5),M20>=LARGE($M$4:$M$31,5)),1,0) -> 0
B21: =IF(H21="","",H21) -> Noemí Castillo | C21: =IF(H21="","",I21/IF(M21="",K21,M21)) -> 0.26315789 | D21: =IF(H21="","",J21/IF(M21="",K21,M21)) -> 0.36842105 | E21: =IF(H21="","",K21/IF(M21="",K21,M21)) -> 0.36842105 | G21: =IFERROR(VLOOKUP(H21,Datos!C:D,2,0),"") -> Norte | H21: Noemí Castillo | I21: 5 | J21: 7 | K21: 7 | L21: 19 | M21: =IF(H21="","",IF(L21="",K21,L21)) -> 19 | N21: =_xlfn.XLOOKUP(H21,Datos!$AT$3:$AT$30,Datos!$AX$3:$AX$30,"") -> 86697.24 | O21: =$N$4 -> 423867.48 | P21: =IF(AND(N21>=LARGE($N$4:$N$31,5),M21>=LARGE($M$4:$M$31,5)),1,0) -> 0
B22: =IF(H22="","",H22) -> Julio César Trejo | C22: =IF(H22="","",I22/IF(M22="",K22,M22)) -> 0.33333333 | D22: =IF(H22="","",J22/IF(M22="",K22,M22)) -> 0.22222222 | E22: =IF(H22="","",K22/IF(M22="",K22,M22)) -> 0.44444444 | G22: =IFERROR(VLOOKUP(H22,Datos!C:D,2,0),"") -> Norte | H22: Julio César Trejo | I22: 6 | J22: 4 | K22: 8 | L22: 18 | M22: =IF(H22="","",IF(L22="",K22,L22)) -> 18 | N22: =_xlfn.XLOOKUP(H22,Datos!$AT$3:$AT$30,Datos!$AX$3:$AX$30,"") -> 251318.64 | O22: =$N$4 -> 423867.48 | P22: =IF(AND(N22>=LARGE($N$4:$N$31,5),M22>=LARGE($M$4:$M$31,5)),1,0) -> 0
B23: =IF(H23="","",H23) -> Giovanni Salas | C23: =IF(H23="","",I23/IF(M23="",K23,M23)) -> 0.26666667 | D23: =IF(H23="","",J23/IF(M23="",K23,M23)) -> 0.4 | E23: =IF(H23="","",K23/IF(M23="",K23,M23)) -> 0.33333333 | G23: =IFERROR(VLOOKUP(H23,Datos!C:D,2,0),"") -> Norte | H23: Giovanni Salas | I23: 4 | J23: 6 | K23: 5 | L23: 15 | M23: =IF(H23="","",IF(L23="",K23,L23)) -> 15 | N23: =_xlfn.XLOOKUP(H23,Datos!$AT$3:$AT$30,Datos!$AX$3:$AX$30,"") -> 263328.12 | O23: =$N$4 -> 423867.48 | P23: =IF(AND(N23>=LARGE($N$4:$N$31,5),M23>=LARGE($M$4:$M$31,5)),1,0) -> 0
B24: =IF(H24="","",H24) -> Jose Carlos Orozco | C24: =IF(H24="","",I24/IF(M24="",K24,M24)) -> 0.21428571 | D24: =IF(H24="","",J24/IF(M24="",K24,M24)) -> 0.071428571 | E24: =IF(H24="","",K24/IF(M24="",K24,M24)) -> 0.71428571 | G24: =IFERROR(VLOOKUP(H24,Datos!C:D,2,0),"") -> Centro | H24: Jose Carlos Orozco | I24: 3 | J24: 1 | K24: 10 | L24: 14 | M24: =IF(H24="","",IF(L24="",K24,L24)) -> 14 | N24: =_xlfn.XLOOKUP(H24,Datos!$AT$3:$AT$30,Datos!$AX$3:$AX$30,"") -> 252958.88 | O24: =$N$4 -> 423867.48 | P24: =IF(AND(N24>=LARGE($N$4:$N$31,5),M24>=LARGE($M$4:$M$31,5)),1,0) -> 0
B25: =IF(H25="","",H25) -> Antonio Salazar | C25: =IF(H25="","",I25/IF(M25="",K25,M25)) -> 0.36363636 | D25: =IF(H25="","",J25/IF(M25="",K25,M25)) -> 0.54545455 | E25: =IF(H25="","",K25/IF(M25="",K25,M25)) -> 0.090909091 | G25: =IFERROR(VLOOKUP(H25,Datos!C:D,2,0),"") -> Norte | H25: Antonio Salazar | I25: 4 | J25: 6 | K25: 1 | L25: 11 | M25: =IF(H25="","",IF(L25="",K25,L25)) -> 11 | N25: =_xlfn.XLOOKUP(H25,Datos!$AT$3:$AT$30,Datos!$AX$3:$AX$30,"") -> 39933 | O25: =$N$4 -> 423867.48 | P25: =IF(AND(N25>=LARGE($N$4:$N$31,5),M25>=LARGE($M$4:$M$31,5)),1,0) -> 0
B26: =IF(H26="","",H26) -> Karla Ángeles | C26: =IF(H26="","",I26/IF(M26="",K26,M26)) -> 0.27272727 | D26: =IF(H26="","",J26/IF(M26="",K26,M26)) -> 0.45454545 | E26: =IF(H26="","",K26/IF(M26="",K26,M26)) -> 0.27272727 | G26: =IFERROR(VLOOKUP(H26,Datos!C:D,2,0),"") -> Centro | H26: Karla Ángeles | I26: 3 | J26: 5 | K26: 3 | L26: 11 | M26: =IF(H26="","",IF(L26="",K26,L26)) -> 11 | N26: =_xlfn.XLOOKUP(H26,Datos!$AT$3:$AT$30,Datos!$AX$3:$AX$30,"") -> 33425.4 | O26: =$N$4 -> 423867.48 | P26: =IF(AND(N26>=LARGE($N$4:$N$31,5),M26>=LARGE($M$4:$M$31,5)),1,0) -> 0
B27: =IF(H27="","",H27) -> Dulce González | C27: =IF(H27="","",I27/IF(M27="",K27,M27)) -> 0.5 | D27: =IF(H27="","",J27/IF(M27="",K27,M27)) -> 0.2 | E27: =IF(H27="","",K27/IF(M27="",K27,M27)) -> 0.3 | G27: =IFERROR(VLOOKUP(H27,Datos!C:D,2,0),"") -> Centro | H27: Dulce González | I27: 5 | J27: 2 | K27: 3 | L27: 10 | M27: =IF(H27="","",IF(L27="",K27,L27)) -> 10 | N27: =_xlfn.XLOOKUP(H27,Datos!$AT$3:$AT$30,Datos!$AX$3:$AX$30,"") -> 78962.209 | O27: =$N$4 -> 423867.48 | P27: =IF(AND(N27>=LARGE($N$4:$N$31,5),M27>=LARGE($M$4:$M$31,5)),1,0) -> 0
B28: =IF(H28="","",H28) -> Roger Gómez | C28: =IF(H28="","",I28/IF(M28="",K28,M28)) -> 0.14285714 | D28: =IF(H28="","",J28/IF(M28="",K28,M28)) -> 0.85714286 | E28: =IF(H28="","",K28/IF(M28="",K28,M28)) -> 0 | G28: =IFERROR(VLOOKUP(H28,Datos!C:D,2,0),"") -> Sur | H28: Roger Gómez | I28: 1 | J28: 6 | L28: 7 | M28: =IF(H28="","",IF(L28="",K28,L28)) -> 7 | N28: =_xlfn.XLOOKUP(H28,Datos!$AT$3:$AT$30,Datos!$AX$3:$AX$30,"") -> 14593.96 | O28: =$N$4 -> 423867.48 | P28: =IF(AND(N28>=LARGE($N$4:$N$31,5),M28>=LARGE($M$4:$M$31,5)),1,0) -> 0
B29: =IF(H29="","",H29) -> David Montañéz | C29: =IF(H29="","",I29/IF(M29="",K29,M29)) -> 0.33333333 | D29: =IF(H29="","",J29/IF(M29="",K29,M29)) -> 0.5 | E29: =IF(H29="","",K29/IF(M29="",K29,M29)) -> 0.16666667 | G29: =IFERROR(VLOOKUP(H29,Datos!C:D,2,0),"") -> Centro | H29: David Montañéz | I29: 2 | J29: 3 | K29: 1 | L29: 6 | M29: =IF(H29="","",IF(L29="",K29,L29)) -> 6 | N29: =_xlfn.XLOOKUP(H29,Datos!$AT$3:$AT$30,Datos!$AX$3:$AX$30,"") -> 16365.28 | O29: =$N$4 -> 423867.48 | P29: =IF(AND(N29>=LARGE($N$4:$N$31,5),M29>=LARGE($M$4:$M$31,5)),1,0) -> 0
B30: =IF(H30="","",H30) -> Noe Acevedo | C30: =IF(H30="","",I30/IF(M30="",K30,M30)) -> 0.4 | D30: =IF(H30="","",J30/IF(M30="",K30,M30)) -> 0.2 | E30: =IF(H30="","",K30/IF(M30="",K30,M30)) -> 0.4 | G30: =IFERROR(VLOOKUP(H30,Datos!C:D,2,0),"") -> Norte | H30: Noe Acevedo | I30: 2 | J30: 1 | K30: 2 | L30: 5 | M30: =IF(H30="","",IF(L30="",K30,L30)) -> 5 | N30: =_xlfn.XLOOKUP(H30,Datos!$AT$3:$AT$30,Datos!$AX$3:$AX$30,"") -> 117243.52 | O30: =$N$4 -> 423867.48 | P30: =IF(AND(N30>=LARGE($N$4:$N$31,5),M30>=LARGE($M$4:$M$31,5)),1,0) -> 0
B31: =IF(H31="","",H31) -> Antonio Hernández | C31: =IF(H31="","",I31/IF(M31="",K31,M31)) -> 1 | D31: =IF(H31="","",J31/IF(M31="",K31,M31)) -> 0 | E31: =IF(H31="","",K31/IF(M31="",K31,M31)) -> 0 | G31: =IFERROR(VLOOKUP(H31,Datos!C:D,2,0),"") -> Norte | H31: Antonio Hernández | I31: 4 | L31: 4 | M31: =IF(H31="","",IF(L31="",K31,L31)) -> 4 | N31: =_xlfn.XLOOKUP(H31,Datos!$AT$3:$AT$30,Datos!$AX$3:$AX$30,"") | O31: =$N$4 -> 423867.48 | P31: =IF(AND(N31>=LARGE($N$4:$N$31,5),M31>=LARGE($M$4:$M$31,5)),1,0) -> 0
B32: =IF(H32="","",H32) -> Carlos Guerra | C32: =IF(H32="","",I32/IF(M32="",K32,M32)) -> 0.25 | D32: =IF(H32="","",J32/IF(M32="",K32,M32)) -> 0.75 | E32: =IF(H32="","",K32/IF(M32="",K32,M32)) -> 0 | G32: =IFERROR(VLOOKUP(H32,Datos!C:D,2,0),"") -> Centro | H32: Carlos Guerra | I32: 1 | J32: 3 | L32: 4 | M32: =IF(H32="","",IF(L32="",K32,L32)) -> 4 | N32: =_xlfn.XLOOKUP(H32,Datos!$AT$3:$AT$30,Datos!$AX$3:$AX$30,"") -> 92933.4
H33: Alondra Díaz | I33: 1 | J33: 2 | L33: 3 | M33: =IF(H33="","",IF(L33="",K33,L33)) -> 3 | N33: =_xlfn.XLOOKUP(H33,Datos!$AT$3:$AT$30,Datos!$AX$3:$AX$30,"") -> 4796.6
H34: Carlos Díaz | I34: 2 | L34: 2 | M34: =IF(H34="","",IF(L34="",K34,L34)) -> 2 | N34: =_xlfn.XLOOKUP(H34,Datos!$AT$3:$AT$30,Datos!$AX$3:$AX$30,"")
H35: Margarita González | I35: 1 | L35: 1 | M35: =IF(H35="","",IF(L35="",K35,L35)) -> 1 | N35: =_xlfn.XLOOKUP(H35,Datos!$AT$3:$AT$30,Datos!$AX$3:$AX$30,"")

Sheet Datos
A1: Fecha de alta | B1: Mes | C1: Ejecutivo | D1: Región | E1: Núm. De cliente | F1: Categoría | G1: Estatus | H1: Meses facturados | I1: Enero | J1: Febrero | K1: Marzo | L1: Abril | M1: Mayo | N1: Junio | O1: Julio | P1: Agosto | Q1: Suma de ventas | R1: Saldo pdte. a junio | S1: Meses facturados | T1: Pagado a junio | U1: % de deuda | V1: Categoría | W1: Categoría de pago | X1: Saldo enero | Y1: Saldo febrero | Z1: Saldo marzo | AA1: Saldo abril | AB1: Saldo Mayo | AC1: Saldo Junio | AD1: Saldo Julio | AE1: Activo/ Inactivo | AQ1: EJECUTIVOS | AR1: REGIÓN | AT1: Suma de Suma de ventas | AU1: Categoría
A2: 44564 | B2: =PROPER(TEXT(A2,"mmmm")) -> Enero | C2: Miguel Romero | D2: =VLOOKUP(Datos!$C2,$AQ$2:$AR$41,2,0) -> Centro | E2: 23080 | F2: {=_xlfn.IFS(H2=0,"Alta sin facturar",H2>2,"Cliente",H2>0,"Cliente nuevo")} -> Alta sin facturar | H2: =COUNTIF(I2:P2,">0") -> 0 | I2: 0 | J2: 0 | K2: 0 | L2: 0 | M2: 0 | N2: 0 | O2: 0 | P2: 0 | Q2: =SUBTOTAL(109,I2:P2) -> 0 | S2: =COUNTIF(I2:P2,">0") -> 0 | T2: =Q2-R2 -> 0 | U2: =IF(Q2=0,0,R2/Q2) -> 0 | V2: {=_xlfn.IFS(S2=0,"Alta sin facturar",S2>2,"Cliente",S2>0,"Cliente nuevo")} -> Alta sin facturar | W2: =IF(T2<1,"Sin pago","Ha pagado") -> Sin pago | AG2: Ejecutivo | AH2: (Todas) | AQ2: Iván Luna | AR2: Norte | AT2: Ejecutivo | AU2: Alta sin facturar | AV2: Cliente nuevo | AW2: Cliente | AX2: Total general
A3: 44564 | B3: =PROPER(TEXT(A3,"mmmm")) -> Enero | C3: Sandra Escoto | D3: =VLOOKUP(Datos!$C3,$AQ$2:$AR$41,2,0) -> Centro | E3: 23081 | F3: {=_xlfn.IFS(H3=0,"Alta sin facturar",H3>2,"Cliente",H3>0,"Cliente nuevo")} -> Cliente | H3: =COUNTIF(I3:P3,">0") -> 8 | I3: 5336 | J3: 5744.32 | K3: 9239.4 | L3: 8745.24 | M3: 6961.16 | N3: 8067.8 | O3: 9052.64 | P3: 8302.12 | Q3: =SUBTOTAL(109,I3:P3) -> 61448.68 | R3: 228.52 | S3: =COUNTIF(I3:P3,">0") -> 8 | T3: =Q3-R3 -> 61220.16 | U3: =IF(Q3=0,0,R3/Q3) -> 0.0037188757 | V3: {=_xlfn.IFS(S3=0,"Alta sin facturar",S3>2,"Cliente",S3>0,"Cliente nuevo")} -> Cliente | W3: =IF(T3<1,"Sin pago","Ha pagado") -> Ha pagado | AQ3: Jesús Hernández | AR3: Centro | AT3: Antonio Salazar | AU3: 0 | AV3: 36884.52 | AW3: 3048.48 | AX3: 39933
A4: 44564 | B4: =PROPER(TEXT(A4,"mmmm")) -> Enero | C4: Sandra Escoto | D4: =VLOOKUP(Datos!$C4,$AQ$2:$AR$41,2,0) -> Centro | E4: 23082 | F4: {=_xlfn.IFS(H4=0,"Alta sin facturar",H4>2,"Cliente",H4>0,"Cliente nuevo")} -> Alta sin facturar | H4: =COUNTIF(I4:P4,">0") -> 0 | I4: 0 | J4: 0 | K4: 0 | L4: 0 | M4: 0 | N4: 0 | O4: 0 | P4: 0 | Q4: =SUBTOTAL(109,I4:P4) -> 0 | S4: =COUNTIF(I4:P4,">0") -> 0 | T4: =Q4-R4 -> 0 | U4: =IF(Q4=0,0,R4/Q4) -> 0 | V4: {=_xlfn.IFS(S4=0,"Alta sin facturar",S4>2,"Cliente",S4>0,"Cliente nuevo")} -> Alta sin facturar | W4: =IF(T4<1,"Sin pago","Ha pagado") -> Sin pago | AG4: Altas | AH4: Categoría | AQ4: PENDIENTE | AR4: Centro | AT4: Blanca Montoya | AU4: 0 | AV4: 27668.32 | AW4: 56562.76 | AX4: 84231.08
A5: 44565 | B5: =PROPER(TEXT(A5,"mmmm")) -> Enero | C5: Marcos López | D5: =VLOOKUP(Datos!$C5,$AQ$2:$AR$41,2,0) -> Sur | E5: 23083 | F5: {=_xlfn.IFS(H5=0,"Alta sin facturar",H5>2,"Cliente",H5>0,"Cliente nuevo")} -> Cliente nuevo | H5: =COUNTIF(I5:P5,">0") -> 2 | I5: 0 | J5: 0 | K5: 0 | L5: 0 | M5: 0 | N5: 690.2 | O5: 0 | P5: 1372.28 | Q5: =SUBTOTAL(109,I5:P5) -> 2062.48 | R5: 302.76 | S5: =COUNTIF(I5:P5,">0") -> 2 | T5: =Q5-R5 -> 1759.72 | U5: =IF(Q5=0,0,R5/Q5) -> 0.14679415 | V5: {=_xlfn.IFS(S5=0,"Alta sin facturar",S5>2,"Cliente",S5>0,"Cliente nuevo")} -> Cliente nuevo | W5: =IF(T5<1,"Sin pago","Ha pagado") -> Ha pagado | AG5: Mes | AH5: Alta sin facturar | AI5: Cliente | AJ5: Cliente nuevo | AK5: Total general | AQ5: Carlos Guerra | AR5: Centro | AT5: Cancelada | AU5: 0 | AX5: 0
A6: 44565 | B6: =PROPER(TEXT(A6,"mmmm")) -> Enero | C6: Yuriana Argüello | D6: =VLOOKUP(Datos!$C6,$AQ$2:$AR$41,2,0) -> Centro | E6: 23084 | F6: {=_xlfn.IFS(H6=0,"Alta sin facturar",H6>2,"Cliente",H6>0,"Cliente nuevo")} -> Cliente nuevo | H6: =COUNTIF(I6:P6,">0") -> 2 | I6: 0 | J6: 0 | K6: 0 | L6: 0 | M6: 0 | N6: 9320.6 | O6: 0 | P6: 221.56 | Q6: =SUBTOTAL(109,I6:P6) -> 9542.16 | R6: 324.8 | S6: =COUNTIF(I6:P6,">0") -> 2 | T6: =Q6-R6 -> 9217.36 | U6: =IF(Q6=0,0,R6/Q6) -> 0.034038415 | V6: {=_xlfn.IFS(S6=0,"Alta sin facturar",S6>2,"Cliente",S6>0,"Cliente nuevo")} -> Cliente nuevo | W6: =IF(T6<1,"Sin pago","Ha pagado") -> Ha pagado | AG6: Enero | AH6: 55 | AI6: 42 | AJ6: 35 | AK6: 132 | AQ6: Blanca Montoya | AR6: Centro | AT6: Christian Castellanos | AU6: 0 | AV6: 26464.24 | AW6: 809691.6 | AX6: 836155.84
A7: 44565 | B7: =PROPER(TEXT(A7,"mmmm")) -> Enero | C7: Yareli Flores | D7: =VLOOKUP(Datos!$C7,$AQ$2:$AR$41,2,0) -> Centro | E7: 23085 | F7: {=_xlfn.IFS(H7=0,"Alta sin facturar",H7>2,"Cliente",H7>0,"Cliente nuevo")} -> Alta sin facturar | H7: =COUNTIF(I7:P7,">0") -> 0 | I7: 0 | J7: 0 | K7: 0 | L7: 0 | M7: 0 | N7: 0 | O7: 0 | P7: 0 | Q7: =SUBTOTAL(109,I7:P7) -> 0 | R7: 8700 | S7: =COUNTIF(I7:P7,">0") -> 0 | T7: =Q7-R7 -> -8700 | U7: =IF(Q7=0,0,R7/Q7) -> 0 | V7: {=_xlfn.IFS(S7=0,"Alta sin facturar",S7>2,"Cliente",S7>0,"Cliente nuevo")} -> Alta sin facturar | W7: =IF(T7<1,"Sin pago","Ha pagado") -> Sin pago | AG7: Febrero | AH7: 28 | AI7: 28 | AJ7: 23 | AK7: 79 | AQ7: Yuriana Argüello | AR7: Centro | AT7: Diana Tejadilla | AU7: 0 | AV7: 21475.08 | AW7: 97147.68 | AX7: 118622.76
A8: 44567 | B8: =PROPER(TEXT(A8,"mmmm")) -> Enero | C8: Yuritzi Alejo | D8: =VLOOKUP(Datos!$C8,$AQ$2:$AR$41,2,0) -> Centro | E8: 23086 | F8: {=_xlfn.IFS(H8=0,"Alta sin facturar",H8>2,"Cliente",H8>0,"Cliente nuevo")} -> Cliente | H8: =COUNTIF(I8:P8,">0") -> 4 | I8: 2.32 | J8: 0 | K8: 0 | L8: 0 | M8: 290 | N8: 21460 | O8: 870 | P8: 0 | Q8: =SUBTOTAL(109,I8:P8) -> 22622.32 | R8: 3480 | S8: =COUNTIF(I8:P8,">0") -> 4 | T8: =Q8-R8 -> 19142.32 | U8: =IF(Q8=0,0,R8/Q8) -> 0.15383038 | V8: {=_xlfn.IFS(S8=0,"Alta sin facturar",S8>2,"Cliente",S8>0,"Cliente nuevo")} -> Cliente | W8: =IF(T8<1,"Sin pago","Ha pagado") -> Ha pagado | AG8: Marzo | AH8: 33 | AI8: 37 | AJ8: 24 | AK8: 94 | AQ8: Miguel Romero | AR8: Centro | AT8: Genaro Castro | AU8: 0 | AV8: 85880.6 | AW8: 295964.72 | AX8: 381845.32
A9: 44567 | B9: =PROPER(TEXT(A9,"mmmm")) -> Enero | C9: Yareli Flores | D9: =VLOOKUP(Datos!$C9,$AQ$2:$AR$41,2,0) -> Centro | E9: 23087 | F9: {=_xlfn.IFS(H9=0,"Alta sin facturar",H9>2,"Cliente",H9>0,"Cliente nuevo")} -> Cliente | H9: =COUNTIF(I9:P9,">0") -> 5 | I9: 1624 | J9: 0 | K9: 0 | L9: 870 | M9: 0 | N9: 5684 | O9: 870 | P9: 1392 | Q9: =SUBTOTAL(109,I9:P9) -> 10440 | R9: 2494 | S9: =COUNTIF(I9:P9,">0") -> 5 | T9: =Q9-R9 -> 7946 | U9: =IF(Q9=0,0,R9/Q9) -> 0.23888889 | V9: {=_xlfn.IFS(S9=0,"Alta sin facturar",S9>2,"Cliente",S9>0,"Cliente nuevo")} -> Cliente | W9: =IF(T9<1,"Sin pago","Ha pagado") -> Ha pagado | AG9: Abril | AH9: 18 | AI9: 36 | AJ9: 22 | AK9: 76 | AQ9: Dolores Jiménez | AR9: Norte | AT9: Giovanni Salas | AU9: 0 | AV9: 14687.92 | AW9: 248640.2 | AX9: 263328.12
A10: 44567 | B10: =PROPER(TEXT(A10,"mmmm")) -> Enero | C10: Genaro Castro | D10: =VLOOKUP(Datos!$C10,$AQ$2:$AR$41,2,0) -> Sur | E10: 23088 | F10: {=_xlfn.IFS(H10=0,"Alta sin facturar",H10>2,"Cliente",H10>0,"Cliente nuevo")} -> Alta sin facturar | H10: =COUNTIF(I10:P10,">0") -> 0 | I10: 0 | J10: 0 | K10: 0 | L10: 0 | M10: 0 | N10: 0 | O10: 0 | P10: 0 | Q10: =SUBTOTAL(109,I10:P10) -> 0 | S10: =COUNTIF(I10:P10,">0") -> 0 | T10: =Q10-R10 -> 0 | U10: =IF(Q10=0,0,R10/Q10) -> 0 | V10: {=_xlfn.IFS(S10=0,"Alta sin facturar",S10>2,"Cliente",S10>0,"Cliente nuevo")} -> Alta sin facturar | W10: =IF(T10<1,"Sin pago","Ha pagado") -> Sin pago | AG10: Mayo | AH10: 20 | AI10: 31 | AJ10: 26 | AK10: 77 | AQ10: Marcos López | AR10: Sur | AT10: Noe Acevedo | AU10: 0 | AV10: 5936.88 | AW10: 111306.64 | AX10: 117243.52
A11: 44567 | B11: =PROPER(TEXT(A11,"mmmm")) -> Enero | C11: Marcos López | D11: =VLOOKUP(Datos!$C11,$AQ$2:$AR$41,2,0) -> Sur | E11: 23089 | F11: {=_xlfn.IFS(H11=0,"Alta sin facturar",H11>2,"Cliente",H11>0,"Cliente nuevo")} -> Cliente nuevo | H11: =COUNTIF(I11:P11,">0") -> 2 | I11: 0 | J11: 0 | K11: 0 | L11: 0 | M11: 0 | N11: 2304.92 | O11: 0 | P11: 1083.44 | Q11: =SUBTOTAL(109,I11:P11) -> 3388.36 | R11: 428.04 | S11: =COUNTIF(I11:P11,">0") -> 2 | T11: =Q11-R11 -> 2960.32 | U11: =IF(Q11=0,0,R11/Q11) -> 0.1263266 | V11: {=_xlfn.IFS(S11=0,"Alta sin facturar",S11>2,"Cliente",S11>0,"Cliente nuevo")} -> Cliente nuevo | W11: =IF(T11<1,"Sin pago","Ha pagado") -> Ha pagado | AG11: Junio | AH11: 27 | AI11: 24 | AJ11: 50 | AK11: 101 | AQ11: Christian Castellanos | AR11: Norte | AT11: Oscar Moreno | AU11: 0 | AV11: 99958.36 | AX11: 99958.36
A12: 44567 | B12: =PROPER(TEXT(A12,"mmmm")) -> Enero | C12: Dulce González | D12: =VLOOKUP(Datos!$C12,$AQ$2:$AR$41,2,0) -> Centro | E12: 23090 | F12: {=_xlfn.IFS(H12=0,"Alta sin facturar",H12>2,"Cliente",H12>0,"Cliente nuevo")} -> Alta sin facturar | H12: =COUNTIF(I12:P12,">0") -> 0 | I12: 0 | J12: 0 | K12: 0 | L12: 0 | M12: 0 | N12: 0 | O12: 0 | P12: 0 | Q12: =SUBTOTAL(109,I12:P12) -> 0 | S12: =COUNTIF(I12:P12,">0") -> 0 | T12: =Q12-R12 -> 0 | U12: =IF(Q12=0,0,R12/Q12) -> 0 | V12: {=_xlfn.IFS(S12=0,"Alta sin facturar",S12>2,"Cliente",S12>0,"Cliente nuevo")} -> Alta sin facturar | W12: =IF(T12<1,"Sin pago","Ha pagado") -> Sin pago | AG12: Julio | AH12: 36 | AJ12: 56 | AK12: 92 | AQ12: Karla Ángeles | AR12: Centro | AT12: Ricardo Vidal | AU12: 0 | AV12: 69149.92 | AW12: 187642.76 | AX12: 256792.68
A13: 44567 | B13: =PROPER(TEXT(A13,"mmmm")) -> Enero | C13: Yareli Flores | D13: =VLOOKUP(Datos!$C13,$AQ$2:$AR$41,2,0) -> Centro | E13: 23091 | F13: {=_xlfn.IFS(H13=0,"Alta sin facturar",H13>2,"Cliente",H13>0,"Cliente nuevo")} -> Cliente | H13: =COUNTIF(I13:P13,">0") -> 3 | I13: 0 | J13: 0 | K13: 747.04 | L13: 174 | M13: 0 | N13: 1624 | O13: 0 | P13: 0 | Q13: =SUBTOTAL(109,I13:P13) -> 2545.04 | R13: 2371.04 | S13: =COUNTIF(I13:P13,">0") -> 3 | T13: =Q13-R13 -> 174 | U13: =IF(Q13=0,0,R13/Q13) -> 0.93163172 | V13: {=_xlfn.IFS(S13=0,"Alta sin facturar",S13>2,"Cliente",S13>0,"Cliente nuevo")} -> Cliente | W13: =IF(T13<1,"Sin pago","Ha pagado") -> Ha pagado | AG13: Agosto | AH13: 62 | AJ13: 13 | AK13: 75 | AQ13: David Montañéz | AR13: Centro | AT13: Sandra Escoto | AU13: 0 | AV13: 2702.8 | AW13: 215327.32 | AX13: 218030.12
A14: 44567 | B14: =PROPER(TEXT(A14,"mmmm")) -> Enero | C14: Iván Luna | D14: =VLOOKUP(Datos!$C14,$AQ$2:$AR$41,2,0) -> Norte | E14: 23092 | F14: {=_xlfn.IFS(H14=0,"Alta sin facturar",H14>2,"Cliente",H14>0,"Cliente nuevo")} -> Cliente | H14: =COUNTIF(I14:P14,">0") -> 8 | I14: 205253.88 | J14: 380995.04 | K14: 335546.24 | L14: 351265.4 | M14: 292277.08 | N14: 453933.52 | O14: 387232.36 | P14: 313720.84 | Q14: =SUBTOTAL(109,I14:P14) -> 2720224.4 | R14: 841165.88 | S14: =COUNTIF(I14:P14,">0") -> 8 | T14: =Q14-R14 -> 1879058.5 | U14: =IF(Q14=0,0,R14/Q14) -> 0.30922666 | V14: {=_xlfn.IFS(S14=0,"Alta sin facturar",S14>2,"Cliente",S14>0,"Cliente nuevo")} -> Cliente | W14: =IF(T14<1,"Sin pago","Ha pagado") -> Ha pagado | AG14: Total general | AH14: 279 | AI14: 198 | AJ14: 249 | AK14: 726 | AQ14: Diana Tejadilla | AR14: Centro | AT14: Yareli Flores | AU14: 0 | AV14: 49410.2 | AW14: 374457.28 | AX14: 423867.48
A15: 44567 | B15: =PROPER(TEXT(A15,"mmmm")) -> Enero | C15: Dolores Jiménez | D15: =VLOOKUP(Datos!$C15,$AQ$2:$AR$41,2,0) -> Norte | E15: 23093 | F15: {=_xlfn.IFS(H15=0,"Alta sin facturar",H15>2,"Cliente",H15>0,"Cliente nuevo")} -> Alta sin facturar | H15: =COUNTIF(I15:P15,">0") -> 0 | I15: 0 | J15: 0 | K15: 0 | L15: 0 | M15: 0 | N15: 0 | O15: 0 | P15: 0 | Q15: =SUBTOTAL(109,I15:P15) -> 0 | S15: =COUNTIF(I15:P15,">0") -> 0 | T15: =Q15-R15 -> 0 | U15: =IF(Q15=0,0,R15/Q15) -> 0 | V15: {=_xlfn.IFS(S15=0,"Alta sin facturar",S15>2,"Cliente",S15>0,"Cliente nuevo")} -> Alta sin facturar | W15: =IF(T15<1,"Sin pago","Ha pagado") -> Sin pago | AQ15: Noemí Castillo | AR15: Norte | AT15: Yuritzi Alejo | AU15: 0 | AV15: 12541.92 | AW15: 759737.94 | AX15: 772279.86
A16: 44568 | B16: =PROPER(TEXT(A16,"mmmm")) -> Enero | C16: Yuriana Argüello | D16: =VLOOKUP(Datos!$C16,$AQ$2:$AR$41,2,0) -> Centro | E16: 23094 | F16: {=_xlfn.IFS(H16=0,"Alta sin facturar",H16>2,"Cliente",H16>0,"Cliente nuevo")} -> Cliente | H16: =COUNTIF(I16:P16,">0") -> 3 | I16: 0 | J16: 0 | K16: 5800 | L16: 11600 | M16: 0 | N16: 262392 | O16: 0 | P16: 0 | Q16: =SUBTOTAL(109,I16:P16) -> 279792 | R16: 49590 | S16: =COUNTIF(I16:P16,">0") -> 3 | T16: =Q16-R16 -> 230202 | U16: =IF(Q16=0,0,R16/Q16) -> 0.17723881 | V16: {=_xlfn.IFS(S16=0,"Alta sin facturar",S16>2,"Cliente",S16>0,"Cliente nuevo")} -> Cliente | W16: =IF(T16<1,"Sin pago","Ha pagado") -> Ha pagado | AQ16: Oscar Moreno | AR16: Magallanes | AT16: Iván Luna | AU16: 0 | AV16: 70870.2 | AW16: 2877402 | AX16: 2948272.2
A17: 44568 | B17: =PROPER(TEXT(A17,"mmmm")) -> Enero | C17: Karla Ángeles | D17: =VLOOKUP(Datos!$C17,$AQ$2:$AR$41,2,0) -> Centro | E17: 23095 | F17: {=_xlfn.IFS(H17=0,"Alta sin facturar",H17>2,"Cliente",H17>0,"Cliente nuevo")} -> Cliente | H17: =COUNTIF(I17:P17,">0") -> 3 | I17: 534.76 | J17: 870 | K17: 0 | L17: 0 | M17: 0 | N17: 1102 | O17: 0 | P17: 0 | Q17: =SUBTOTAL(109,I17:P17) -> 2506.76 | R17: 1102 | S17: =COUNTIF(I17:P17,">0") -> 3 | T17: =Q17-R17 -> 1404.76 | U17: =IF(Q17=0,0,R17/Q17) -> 0.43961129 | V17: {=_xlfn.IFS(S17=0,"Alta sin facturar",S17>2,"Cliente",S17>0,"Cliente nuevo")} -> Cliente | W17: =IF(T17<1,"Sin pago","Ha pagado") -> Ha pagado | AG17: Ejecutivo | AH17: (Todas) | AQ17: Julio Trejo | AR17: Norte | AT17: Alfredo Almaráz | AU17: 0 | AV17: 104077.52 | AW17: 357601.32 | AX17: 461678.84
A18: 44569 | B18: =PROPER(TEXT(A18,"mmmm")) -> Enero | C18: Yuritzi Alejo | D18: =VLOOKUP(Datos!$C18,$AQ$2:$AR$41,2,0) -> Centro | E18: 23096 | F18: {=_xlfn.IFS(H18=0,"Alta sin facturar",H18>2,"Cliente",H18>0,"Cliente nuevo")} -> Alta sin facturar | H18: =COUNTIF(I18:P18,">0") -> 0 | I18: 0 | J18: 0 | K18: 0 | L18: 0 | M18: 0 | N18: 0 | O18: 0 | P18: 0 | Q18: =SUBTOTAL(109,I18:P18) -> 0 | R18: 928 | S18: =COUNTIF(I18:P18,">0") -> 0 | T18: =Q18-R18 -> -928 | U18: =IF(Q18=0,0,R18/Q18) -> 0 | V18: {=_xlfn.IFS(S18=0,"Alta sin facturar",S18>2,"Cliente",S18>0,"Cliente nuevo")} -> Alta sin facturar | W18: =IF(T18<1,"Sin pago","Ha pagado") -> Sin pago | AQ18: Genaro Castro | AR18: Sur | AT18: Noemí Castillo | AU18: 0 | AV18: 21712.88 | AW18: 64984.36 | AX18: 86697.24
A19: 44569 | B19: =PROPER(TEXT(A19,"mmmm")) -> Enero | C19: Alfredo Almaráz | D19: =VLOOKUP(Datos!$C19,$AQ$2:$AR$41,2,0) -> Magallanes | E19: 23097 | F19: {=_xlfn.IFS(H19=0,"Alta sin facturar",H19>2,"Cliente",H19>0,"Cliente nuevo")} -> Alta sin facturar | H19: =COUNTIF(I19:P19,">0") -> 0 | I19: 0 | J19: 0 | K19: 0 | L19: 0 | M19: 0 | N19: 0 | O19: 0 | P19: 0 | Q19: =SUBTOTAL(109,I19:P19) -> 0 | R19: 10211.48 | S19: =COUNTIF(I19:P19,">0") -> 0 | T19: =Q19-R19 -> -10211.48 | U19: =IF(Q19=0,0,R19/Q19) -> 0 | V19: {=_xlfn.IFS(S19=0,"Alta sin facturar",S19>2,"Cliente",S19>0,"Cliente nuevo")} -> Alta sin facturar | W19: =IF(T19<1,"Sin pago","Ha pagado") -> Sin pago | AG19: Suma de venta | AH19: Categoría | AQ19: Giovanni Salas | AR19: Norte | AT19: Marcos López | AU19: 0 | AV19: 312603.76 | AX19: 312603.76
A20: 44569 | B20: =PROPER(TEXT(A20,"mmmm")) -> Enero | C20: Alfredo Almaráz | D20: =VLOOKUP(Datos!$C20,$AQ$2:$AR$41,2,0) -> Magallanes | E20: 23098 | F20: {=_xlfn.IFS(H20=0,"Alta sin facturar",H20>2,"Cliente",H20>0,"Cliente nuevo")} -> Alta sin facturar | H20: =COUNTIF(I20:P20,">0") -> 0 | I20: 0 | J20: 0 | K20: 0 | L20: 0 | M20: 0 | N20: 0 | O20: 0 | P20: 0 | Q20: =SUBTOTAL(109,I20:P20) -> 0 | R20: 24.36 | S20: =COUNTIF(I20:P20,">0") -> 0 | T20: =Q20-R20 -> -24.36 | U20: =IF(Q20=0,0,R20/Q20) -> 0 | V20: {=_xlfn.IFS(S20=0,"Alta sin facturar",S20>2,"Cliente",S20>0,"Cliente nuevo")} -> Alta sin facturar | W20: =IF(T20<1,"Sin pago","Ha pagado") -> Sin pago | AG20: Mes | AH20: Alta sin facturar | AI20: Cliente | AJ20: Cliente nuevo | AK20: Total general | AQ20: Alfredo Orta | AR20: Centro | AT20: Dolores Jiménez | AU20: 0 | AV20: 12380.68 | AW20: 323878.96 | AX20: 336259.64
A21: 44569 | B21: =PROPER(TEXT(A21,"mmmm")) -> Enero | C21: Alfredo Almaráz | D21: =VLOOKUP(Datos!$C21,$AQ$2:$AR$41,2,0) -> Magallanes | E21: 23099 | F21: {=_xlfn.IFS(H21=0,"Alta sin facturar",H21>2,"Cliente",H21>0,"Cliente nuevo")} -> Cliente | H21: =COUNTIF(I21:P21,">0") -> 6 | I21: 0 | J21: 348 | K21: 0 | L21: 696 | M21: 116 | N21: 395.56 | O21: 627.56 | P21: 4127.28 | Q21: =SUBTOTAL(109,I21:P21) -> 6310.4 | R21: 696 | S21: =COUNTIF(I21:P21,">0") -> 6 | T21: =Q21-R21 -> 5614.4 | U21: =IF(Q21=0,0,R21/Q21) -> 0.11029412 | V21: {=_xlfn.IFS(S21=0,"Alta sin facturar",S21>2,"Cliente",S21>0,"Cliente nuevo")} -> Cliente | W21: =IF(T21<1,"Sin pago","Ha pagado") -> Ha pagado | AG21: Enero | AH21: 0 | AI21: 4216487.5 | AJ21: 239243.04 | AK21: 4455730.5 | AQ21: Ricardo Vidal | AR21: Magallanes | AT21: Julio César Trejo | AU21: 0 | AV21: 15404.8 | AW21: 235913.84 | AX21: 251318.64
A22: 44571 | B22: =PROPER(TEXT(A22,"mmmm")) -> Enero | C22: Yuritzi Alejo | D22: =VLOOKUP(Datos!$C22,$AQ$2:$AR$41,2,0) -> Centro | E22: 23100 | F22: {=_xlfn.IFS(H22=0,"Alta sin facturar",H22>2,"Cliente",H22>0,"Cliente nuevo")} -> Alta sin facturar | H22: =COUNTIF(I22:P22,">0") -> 0 | I22: 0 | J22: 0 | K22: 0 | L22: 0 | M22: 0 | N22: 0 | O22: 0 | P22: 0 | Q22: =SUBTOTAL(109,I22:P22) -> 0 | S22: =COUNTIF(I22:P22,">0") -> 0 | T22: =Q22-R22 -> 0 | U22: =IF(Q22=0,0,R22/Q22) -> 0 | V22: {=_xlfn.IFS(S22=0,"Alta sin facturar",S22>2,"Cliente",S22>0,"Cliente nuevo")} -> Alta sin facturar | W22: =IF(T22<1,"Sin pago","Ha pagado") -> Sin pago | AG22: Febrero | AH22: 0 | AI22: 923884.32 | AJ22: 139022.52 | AK22: 1062906.8 | AQ22: Rubí Rodríguez | AR22: Centro | AT22: Karla Ángeles | AU22: 0 | AV22: 19062.28 | AW22: 14363.12 | AX22: 33425.4
A23: 44571 | B23: =PROPER(TEXT(A23,"mmmm")) -> Enero | C23: Yuritzi Alejo | D23: =VLOOKUP(Datos!$C23,$AQ$2:$AR$41,2,0) -> Centro | E23: 23101 | F23: {=_xlfn.IFS(H23=0,"Alta sin facturar",H23>2,"Cliente",H23>0,"Cliente nuevo")} -> Alta sin facturar | H23: =COUNTIF(I23:P23,">0") -> 0 | I23: 0 | J23: 0 | K23: 0 | L23: 0 | M23: 0 | N23: 0 | O23: 0 | P23: 0 | Q23: =SUBTOTAL(109,I23:P23) -> 0 | R23: 0 | S23: =COUNTIF(I23:P23,">0") -> 0 | T23: =Q23-R23 -> 0 | U23: =IF(Q23=0,0,R23/Q23) -> 0 | V23: {=_xlfn.IFS(S23=0,"Alta sin facturar",S23>2,"Cliente",S23>0,"Cliente nuevo")} -> Alta sin facturar | W23: =IF(T23<1,"Sin pago","Ha pagado") -> Sin pago | AG23: Marzo | AH23: 0 | AI23: 964667.6 | AJ23: 98967.72 | AK23: 1063635.3 | AQ23: Antonio Hernández | AR23: Norte | AT23: Dulce González | AU23: 0 | AV23: 29568.249 | AW23: 49393.96 | AX23: 78962.209
A24: 44571 | B24: =PROPER(TEXT(A24,"mmmm")) -> Enero | C24: Sandra Escoto | D24: =VLOOKUP(Datos!$C24,$AQ$2:$AR$41,2,0) -> Centro | E24: 23102 | F24: {=_xlfn.IFS(H24=0,"Alta sin facturar",H24>2,"Cliente",H24>0,"Cliente nuevo")} -> Cliente | H24: =COUNTIF(I24:P24,">0") -> 7 | I24: 725 | J24: 0 | K24: 3528.72 | L24: 5274.52 | M24: 2395.4 | N24: 1633.28 | O24: 5761.72 | P24: 7464.6 | Q24: =SUBTOTAL(109,I24:P24) -> 26783.24 | R24: 0 | S24: =COUNTIF(I24:P24,">0") -> 7 | T24: =Q24-R24 -> 26783.24 | U24: =IF(Q24=0,0,R24/Q24) -> 0 | V24: {=_xlfn.IFS(S24=0,"Alta sin facturar",S24>2,"Cliente",S24>0,"Cliente nuevo")} -> Cliente | W24: =IF(T24<1,"Sin pago","Ha pagado") -> Ha pagado | AG24: Abril | AH24: 0 | AI24: 1000965.7 | AJ24: 43425.609 | AK24: 1044391.3 | AQ24: Dulce González | AR24: Centro | AT24: Jose Carlos Orozco | AU24: 0 | AV24: 81.2 | AW24: 252877.68 | AX24: 252958.88
A25: 44571 | B25: =PROPER(TEXT(A25,"mmmm")) -> Enero | C25: Sandra Escoto | D25: =VLOOKUP(Datos!$C25,$AQ$2:$AR$41,2,0) -> Centro | E25: 23103 | F25: {=_xlfn.IFS(H25=0,"Alta sin facturar",H25>2,"Cliente",H25>0,"Cliente nuevo")} -> Cliente | H25: =COUNTIF(I25:P25,">0") -> 4 | I25: 0 | J25: 0 | K25: 812 | L25: 0 | M25: 0 | N25: 9686 | O25: 1740 | P25: 1740 | Q25: =SUBTOTAL(109,I25:P25) -> 13978 | R25: 0 | S25: =COUNTIF(I25:P25,">0") -> 4 | T25: =Q25-R25 -> 13978 | U25: =IF(Q25=0,0,R25/Q25) -> 0 | V25: {=_xlfn.IFS(S25=0,"Alta sin facturar",S25>2,"Cliente",S25>0,"Cliente nuevo")} -> Cliente | W25: =IF(T25<1,"Sin pago","Ha pagado") -> Ha pagado | AG25: Mayo | AH25: 0 | AI25: 523948.8 | AJ25: 285948.12 | AK25: 809896.92 | AQ25: Magallanes | AR25: Magallanes | AT25: Carlos Guerra | AU25: 0 | AV25: 92933.4 | AX25: 92933.4
A26: 44571 | B26: =PROPER(TEXT(A26,"mmmm")) -> Enero | C26: Dolores Jiménez | D26: =VLOOKUP(Datos!$C26,$AQ$2:$AR$41,2,0) -> Norte | E26: 23104 | F26: {=_xlfn.IFS(H26=0,"Alta sin facturar",H26>2,"Cliente",H26>0,"Cliente nuevo")} -> Cliente | H26: =COUNTIF(I26:P26,">0") -> 6 | I26: 0 | J26: 1252.8 | K26: 0 | L26: 3949.8 | M26: 7078.32 | N26: 3289.76 | O26: 2485.88 | P26: 3384.88 | Q26: =SUBTOTAL(109,I26:P26) -> 21441.44 | R26: 0 | S26: =COUNTIF(I26:P26,">0") -> 6 | T26: =Q26-R26 -> 21441.44 | U26: =IF(Q26=0,0,R26/Q26) -> 0 | V26: {=_xlfn.IFS(S26=0,"Alta sin facturar",S26>2,"Cliente",S26>0,"Cliente nuevo")} -> Cliente | W26: =IF(T26<1,"Sin pago","Ha pagado") -> Ha pagado | AG26: Junio | AH26: 0 | AI26: 422584.52 | AJ26: 231706.52 | AK26: 654291.04 | AQ26: Antonio Salazar | AR26: Norte | AT26: Yuriana Argüello | AU26: 0 | AV26: 39543.24 | AW26: 279792 | AX26: 319335.24
A27: 44572 | B27: =PROPER(TEXT(A27,"mmmm")) -> Enero | C27: Rubí Rodríguez | D27: =VLOOKUP(Datos!$C27,$AQ$2:$AR$41,2,0) -> Centro | E27: 23105 | F27: {=_xlfn.IFS(H27=0,"Alta sin facturar",H27>2,"Cliente",H27>0,"Cliente nuevo")} -> Cliente nuevo | H27: =COUNTIF(I27:P27,">0") -> 2 | I27: 0 | J27: 0 | K27: 0 | L27: 580 | M27: 0 | N27: 580 | O27: 0 | P27: 0 | Q27: =SUBTOTAL(109,I27:P27) -> 1160 | R27: 0 | S27: =COUNTIF(I27:P27,">0") -> 2 | T27: =Q27-R27 -> 1160 | U27: =IF(Q27=0,0,R27/Q27) -> 0 | V27: {=_xlfn.IFS(S27=0,"Alta sin facturar",S27>2,"Cliente",S27>0,"Cliente nuevo")} -> Cliente nuevo | W27: =IF(T27<1,"Sin pago","Ha pagado") -> Ha pagado | AG27: Julio | AH27: 0 | AJ27: 251399.84 | AK27: 251399.84 | AQ27: Telemarketing | AR27: Norte | AT27: Alondra Díaz | AU27: 0 | AV27: 4796.6 | AX27: 4796.6
A28: 44572 | B28: =PROPER(TEXT(A28,"mmmm")) -> Enero | C28: Yuritzi Alejo | D28: =VLOOKUP(Datos!$C28,$AQ$2:$AR$41,2,0) -> Centro | E28: 23106 | F28: {=_xlfn.IFS(H28=0,"Alta sin facturar",H28>2,"Cliente",H28>0,"Cliente nuevo")} -> Alta sin facturar | H28: =COUNTIF(I28:P28,">0") -> 0 | I28: 0 | J28: 0 | K28: 0 | L28: 0 | M28: 0 | N28: 0 | O28: 0 | P28: 0 | Q28: =SUBTOTAL(109,I28:P28) -> 0 | S28: =COUNTIF(I28:P28,">0") -> 0 | T28: =Q28-R28 -> 0 | U28: =IF(Q28=0,0,R28/Q28) -> 0 | V28: {=_xlfn.IFS(S28=0,"Alta sin facturar",S28>2,"Cliente",S28>0,"Cliente nuevo")} -> Alta sin facturar | W28: =IF(T28<1,"Sin pago","Ha pagado") -> Sin pago | AG28: Agosto | AH28: 0 | AJ28: 24922.6 | AK28: 24922.6 | AQ28: Leonard Lule | AR28: Sur | AT28: David Montañéz | AU28: 0 | AV28: 10832.08 | AW28: 5533.2 | AX28: 16365.28
A29: 44572 | B29: =PROPER(TEXT(A29,"mmmm")) -> Enero | C29: Christian Castellanos | D29: =VLOOKUP(Datos!$C29,$AQ$2:$AR$41,2,0) -> Norte | E29: 23107 | F29: {=_xlfn.IFS(H29=0,"Alta sin facturar",H29>2,"Cliente",H29>0,"Cliente nuevo")} -> Cliente | H29: =COUNTIF(I29:P29,">0") -> 8 | I29: 34333.68 | J29: 22338.12 | K29: 34126.04 | L29: 26899.24 | M29: 17278.2 | N29: 46328.08 | O29: 24364.64 | P29: 22100.32 | Q29: =SUBTOTAL(109,I29:P29) -> 227768.32 | R29: 15179.76 | S29: =COUNTIF(I29:P29,">0") -> 8 | T29: =Q29-R29 -> 212588.56 | U29: =IF(Q29=0,0,R29/Q29) -> 0.066645616 | V29: {=_xlfn.IFS(S29=0,"Alta sin facturar",S29>2,"Cliente",S29>0,"Cliente nuevo")} -> Cliente | W29: =IF(T29<1,"Sin pago","Ha pagado") -> Ha pagado | AG29: Total general | AH29: 0 | AI29: 8052538.5 | AJ29: 1314636 | AK29: 9367174.4 | AQ29: Alfredo Almaráz | AR29: Magallanes | AT29: Roger Gómez | AU29: 0 | AV29: 14593.96 | AX29: 14593.96
A30: 44572 | B30: =PROPER(TEXT(A30,"mmmm")) -> Enero | C30: Yuritzi Alejo | D30: =VLOOKUP(Datos!$C30,$AQ$2:$AR$41,2,0) -> Centro | E30: 23108 | F30: {=_xlfn.IFS(H30=0,"Alta sin facturar",H30>2,"Cliente",H30>0,"Cliente nuevo")} -> Cliente | H30: =COUNTIF(I30:P30,">0") -> 7 | I30: 0 | J30: 2148.32 | K30: 1717.96 | L30: 909.44 | M30: 1039.36 | N30: 6173.52 | O30: 1209.88 | P30: 2263.16 | Q30: =SUBTOTAL(109,I30:P30) -> 15461.64 | R30: 0 | S30: =COUNTIF(I30:P30,">0") -> 7 | T30: =Q30-R30 -> 15461.64 | U30: =IF(Q30=0,0,R30/Q30) -> 0 | V30: {=_xlfn.IFS(S30=0,"Alta sin facturar",S30>2,"Cliente",S30>0,"Cliente nuevo")} -> Cliente | W30: =IF(T30<1,"Sin pago","Ha pagado") -> Ha pagado | AQ30: Yareli Flores | AR30: Centro | AT30: Rubí Rodríguez | AU30: 0 | AV30: 37791.64 | AW30: 181559.72 | AX30: 219351.36
A31: 44573 | B31: =PROPER(TEXT(A31,"mmmm")) -> Enero | C31: Marcos López | D31: =VLOOKUP(Datos!$C31,$AQ$2:$AR$41,2,0) -> Sur | E31: 23109 | F31: {=_xlfn.IFS(H31=0,"Alta sin facturar",H31>2,"Cliente",H31>0,"Cliente nuevo")} -> Cliente nuevo | H31: =COUNTIF(I31:P31,">0") -> 2 | I31: 0 | J31: 0 | K31: 0 | L31: 0 | M31: 0 | N31: 546.36 | O31: 0 | P31: 222.72 | Q31: =SUBTOTAL(109,I31:P31) -> 769.08 | R31: 291.16 | S31: =COUNTIF(I31:P31,">0") -> 2 | T31: =Q31-R31 -> 477.92 | U31: =IF(Q31=0,0,R31/Q31) -> 0.3785822 | V31: {=_xlfn.IFS(S31=0,"Alta sin facturar",S31>2,"Cliente",S31>0,"Cliente nuevo")} -> Cliente nuevo | W31: =IF(T31<1,"Sin pago","Ha pagado") -> Ha pagado | AG31: Categoría de pago | AH31: Ha pagado | AQ31: BEST | AR31: Centro | AT31: Miguel Romero | AU31: 0 | AV31: 36221 | AW31: 76814.04 | AX31: 113035.04
A32: 44573 | B32: =PROPER(TEXT(A32,"mmmm")) -> Enero | C32: Jose Carlos Orozco | D32: =VLOOKUP(Datos!$C32,$AQ$2:$AR$41,2,0) -> Centro | E32: 23110 | F32: {=_xlfn.IFS(H32=0,"Alta sin facturar",H32>2,"Cliente",H32>0,"Cliente nuevo")} -> Cliente | H32: =COUNTIF(I32:P32,">0") -> 6 | I32: 487.2 | J32: 629.88 | K32: 1485.96 | L32: 435 | M32: 403.68 | N32: 351.48 | O32: 0 | P32: 0 | Q32: =SUBTOTAL(109,I32:P32) -> 3793.2 | R32: 857.24 | S32: =COUNTIF(I32:P32,">0") -> 6 | T32: =Q32-R32 -> 2935.96 | U32: =IF(Q32=0,0,R32/Q32) -> 0.22599388 | V32: {=_xlfn.IFS(S32=0,"Alta sin facturar",S32>2,"Cliente",S32>0,"Cliente nuevo")} -> Cliente | W32: =IF(T32<1,"Sin pago","Ha pagado") -> Ha pagado | AG32: Ejecutivo | AH32: (Todas) | AQ32: Róger Gómez | AR32: Sur | AT32: Leonard Lule | AU32: 0 | AV32: 39401.72 | AW32: 172896.84 | AX32: 212298.56
A33: 44573 | B33: =PROPER(TEXT(A33,"mmmm")) -> Enero | C33: Rubí Rodríguez | D33: =VLOOKUP(Datos!$C33,$AQ$2:$AR$41,2,0) -> Centro | E33: 23111 | F33: {=_xlfn.IFS(H33=0,"Alta sin facturar",H33>2,"Cliente",H33>0,"Cliente nuevo")} -> Alta sin facturar | H33: =COUNTIF(I33:P33,">0") -> 0 | I33: 0 | J33: 0 | K33: 0 | L33: 0 | M33: 0 | N33: 0 | O33: 0 | P33: 0 | Q33: =SUBTOTAL(109,I33:P33) -> 0 | S33: =COUNTIF(I33:P33,">0") -> 0 | T33: =Q33-R33 -> 0 | U33: =IF(Q33=0,0,R33/Q33) -> 0 | V33: {=_xlfn.IFS(S33=0,"Alta sin facturar",S33>2,"Cliente",S33>0,"Cliente nuevo")} -> Alta sin facturar | W33: =IF(T33<1,"Sin pago","Ha pagado") -> Sin pago | AQ33: Margarita González | AR33: Norte | AT33: Margarita González | AU33: 0 | AX33: 0
A34: 44573 | B34: =PROPER(TEXT(A34,"mmmm")) -> Enero | C34: Yuriana Argüello | D34: =VLOOKUP(Datos!$C34,$AQ$2:$AR$41,2,0) -> Centro | E34: 23112 | F34: {=_xlfn.IFS(H34=0,"Alta sin facturar",H34>2,"Cliente",H34>0,"Cliente nuevo")} -> Alta sin facturar | H34: =COUNTIF(I34:P34,">0") -> 0 | I34: 0 | J34: 0 | K34: 0 | L34: 0 | M34: 0 | N34: 0 | O34: 0 | P34: 0 | Q34: =SUBTOTAL(109,I34:P34) -> 0 | S34: =COUNTIF(I34:P34,">0") -> 0 | T34: =Q34-R34 -> 0 | U34: =IF(Q34=0,0,R34/Q34) -> 0 | V34: {=_xlfn.IFS(S34=0,"Alta sin facturar",S34>2,"Cliente",S34>0,"Cliente nuevo")} -> Alta sin facturar | W34: =IF(T34<1,"Sin pago","Ha pagado") -> Sin pago | AG34: Cuenta de Núm. De cliente | AH34: Pago | AQ34: Carlos Díaz | AR34: Norte | AT34: Antonio Hernández | AU34: 0 | AX34: 0
A35: 44573 | B35: =PROPER(TEXT(A35,"mmmm")) -> Enero | C35: Yuriana Argüello | D35: =VLOOKUP(Datos!$C35,$AQ$2:$AR$41,2,0) -> Centro | E35: 23113 | F35: {=_xlfn.IFS(H35=0,"Alta sin facturar",H35>2,"Cliente",H35>0,"Cliente nuevo")} -> Alta sin facturar | H35: =COUNTIF(I35:P35,">0") -> 0 | I35: 0 | J35: 0 | K35: 0 | L35: 0 | M35: 0 | N35: 0 | O35: 0 | P35: 0 | Q35: =SUBTOTAL(109,I35:P35) -> 0 | S35: =COUNTIF(I35:P35,">0") -> 0 | T35: =Q35-R35 -> 0 | U35: =IF(Q35=0,0,R35/Q35) -> 0 | V35: {=_xlfn.IFS(S35=0,"Alta sin facturar",S35>2,"Cliente",S35>0,"Cliente nuevo")} -> Alta sin facturar | W35: =IF(T35<1,"Sin pago","Ha pagado") -> Sin pago | AG35: Categoría | AH35: Enero | AI35: Febrero | AJ35: Marzo | AK35: Abril | AL35: Mayo | AM35: Junio | AN35: Total general | AQ35: Jose Carlos Orozco | AR35: Centro | AT35: Carlos Díaz | AU35: 0 | AX35: 0
A36: 44573 | B36: =PROPER(TEXT(A36,"mmmm")) -> Enero | C36: Genaro Castro | D36: =VLOOKUP(Datos!$C36,$AQ$2:$AR$41,2,0) -> Sur | E36: 23114 | F36: {=_xlfn.IFS(H36=0,"Alta sin facturar",H36>2,"Cliente",H36>0,"Cliente nuevo")} -> Cliente nuevo | H36: =COUNTIF(I36:P36,">0") -> 2 | I36: 0 | J36: 0 | K36: 0 | L36: 0 | M36: 0 | N36: 91.64 | O36: 0 | P36: 366.56 | Q36: =SUBTOTAL(109,I36:P36) -> 458.2 | R36: 0 | S36: =COUNTIF(I36:P36,">0") -> 2 | T36: =Q36-R36 -> 458.2 | U36: =IF(Q36=0,0,R36/Q36) -> 0 | V36: {=_xlfn.IFS(S36=0,"Alta sin facturar",S36>2,"Cliente",S36>0,"Cliente nuevo")} -> Cliente nuevo | W36: =IF(T36<1,"Sin pago","Ha pagado") -> Ha pagado | AG36: Alta sin facturar | AH36: 13 | AI36: 14 | AJ36: 21 | AK36: 14 | AL36: 11 | AM36: 14 | AN36: 87 | AQ36: Sandra Escoto | AR36: Centro
A37: 44573 | B37: =PROPER(TEXT(A37,"mmmm")) -> Enero | C37: Rubí Rodríguez | D37: =VLOOKUP(Datos!$C37,$AQ$2:$AR$41,2,0) -> Centro | E37: 23115 | F37: {=_xlfn.IFS(H37=0,"Alta sin facturar",H37>2,"Cliente",H37>0,"Cliente nuevo")} -> Cliente nuevo | H37: =COUNTIF(I37:P37,">0") -> 1 | I37: 0 | J37: 0 | K37: 0 | L37: 3424.32 | M37: 0 | N37: 0 | O37: 0 | P37: 0 | Q37: =SUBTOTAL(109,I37:P37) -> 3424.32 | R37: 290 | S37: =COUNTIF(I37:P37,">0") -> 1 | T37: =Q37-R37 -> 3134.32 | U37: =IF(Q37=0,0,R37/Q37) -> 0.084688347 | V37: {=_xlfn.IFS(S37=0,"Alta sin facturar",S37>2,"Cliente",S37>0,"Cliente nuevo")} -> Cliente nuevo | W37: =IF(T37<1,"Sin pago","Ha pagado") -> Ha pagado | AG37: Cliente | AH37: 53 | AI37: 27 | AJ37: 33 | AK37: 25 | AL37: 10 | AM37: 0 | AN37: 148 | AQ37: Julio César Trejo | AR37: Norte
A38: 44573 | B38: =PROPER(TEXT(A38,"mmmm")) -> Enero | C38: Sandra Escoto | D38: =VLOOKUP(Datos!$C38,$AQ$2:$AR$41,2,0) -> Centro | E38: 23116 | F38: {=_xlfn.IFS(H38=0,"Alta sin facturar",H38>2,"Cliente",H38>0,"Cliente nuevo")} -> Cliente | H38: =COUNTIF(I38:P38,">0") -> 3 | I38: 276.08 | J38: 310.88 | K38: 926.84 | L38: 0 | M38: 0 | N38: 0 | O38: 0 | P38: 0 | Q38: =SUBTOTAL(109,I38:P38) -> 1513.8 | R38: 0 | S38: =COUNTIF(I38:P38,">0") -> 3 | T38: =Q38-R38 -> 1513.8 | U38: =IF(Q38=0,0,R38/Q38) -> 0 | V38: {=_xlfn.IFS(S38=0,"Alta sin facturar",S38>2,"Cliente",S38>0,"Cliente nuevo")} -> Cliente | W38: =IF(T38<1,"Sin pago","Ha pagado") -> Ha pagado | AG38: Cliente nuevo | AH38: 13 | AI38: 13 | AJ38: 8 | AK38: 17 | AL38: 29 | AM38: 49 | AN38: 129 | AQ38: Roger Gómez | AR38: Sur
A39: 44574 | B39: =PROPER(TEXT(A39,"mmmm")) -> Enero | C39: Ricardo Vidal | D39: =VLOOKUP(Datos!$C39,$AQ$2:$AR$41,2,0) -> Magallanes | E39: 23117 | F39: {=_xlfn.IFS(H39=0,"Alta sin facturar",H39>2,"Cliente",H39>0,"Cliente nuevo")} -> Cliente | H39: =COUNTIF(I39:P39,">0") -> 5 | I39: 0 | J39: 371.2 | K39: 0 | L39: 0 | M39: 280.72 | N39: 1968.52 | O39: 3811.76 | P39: 2569.4 | Q39: =SUBTOTAL(109,I39:P39) -> 9001.6 | R39: 1856 | S39: =COUNTIF(I39:P39,">0") -> 5 | T39: =Q39-R39 -> 7145.6 | U39: =IF(Q39=0,0,R39/Q39) -> 0.20618557 | V39: {=_xlfn.IFS(S39=0,"Alta sin facturar",S39>2,"Cliente",S39>0,"Cliente nuevo")} -> Cliente | W39: =IF(T39<1,"Sin pago","Ha pagado") -> Ha pagado | AG39: Total general | AH39: 79 | AI39: 54 | AJ39: 62 | AK39: 56 | AL39: 50 | AM39: 63 | AN39: 364 | AQ39: Noe Acevedo | AR39: Norte
A40: 44574 | B40: =PROPER(TEXT(A40,"mmmm")) -> Enero | C40: Yareli Flores | D40: =VLOOKUP(Datos!$C40,$AQ$2:$AR$41,2,0) -> Centro | E40: 23118 | F40: {=_xlfn.IFS(H40=0,"Alta sin facturar",H40>2,"Cliente",H40>0,"Cliente nuevo")} -> Cliente nuevo | H40: =COUNTIF(I40:P40,">0") -> 1 | I40: 0 | J40: 0 | K40: 0 | L40: 0 | M40: 0 | N40: 12992 | O40: 0 | P40: 0 | Q40: =SUBTOTAL(109,I40:P40) -> 12992 | R40: 0 | S40: =COUNTIF(I40:P40,">0") -> 1 | T40: =Q40-R40 -> 12992 | U40: =IF(Q40=0,0,R40/Q40) -> 0 | V40: {=_xlfn.IFS(S40=0,"Alta sin facturar",S40>2,"Cliente",S40>0,"Cliente nuevo")} -> Cliente nuevo | W40: =IF(T40<1,"Sin pago","Ha pagado") -> Ha pagado | AQ40: Alondra Díaz | AR40: Sur
A41: 44574 | B41: =PROPER(TEXT(A41,"mmmm")) -> Enero | C41: Sandra Escoto | D41: =VLOOKUP(Datos!$C41,$AQ$2:$AR$41,2,0) -> Centro | E41: 23119 | F41: {=_xlfn.IFS(H41=0,"Alta sin facturar",H41>2,"Cliente",H41>0,"Cliente nuevo")} -> Alta sin facturar | H41: =COUNTIF(I41:P41,">0") -> 0 | I41: 0 | J41: 0 | K41: 0 | L41: 0 | M41: 0 | N41: 0 | O41: 0 | P41: 0 | Q41: =SUBTOTAL(109,I41:P41) -> 0 | S41: =COUNTIF(I41:P41,">0") -> 0 | T41: =Q41-R41 -> 0 | U41: =IF(Q41=0,0,R41/Q41) -> 0 | V41: {=_xlfn.IFS(S41=0,"Alta sin facturar",S41>2,"Cliente",S41>0,"Cliente nuevo")} -> Alta sin facturar | W41: =IF(T41<1,"Sin pago","Ha pagado") -> Sin pago | AG41: Categoría de pago | AH41: Ha pagado | AQ41: Yuritzi Alejo | AR41: Centro
A42: 44575 | B42: =PROPER(TEXT(A42,"mmmm")) -> Enero | C42: Marcos López | D42: =VLOOKUP(Datos!$C42,$AQ$2:$AR$41,2,0) -> Sur | E42: 23120 | F42: {=_xlfn.IFS(H42=0,"Alta sin facturar",H42>2,"Cliente",H42>0,"Cliente nuevo")} -> Cliente nuevo | H42: =COUNTIF(I42:P42,">0") -> 2 | I42: 0 | J42: 0 | K42: 0 | L42: 0 | M42: 0 | N42: 13014.04 | O42: 0 | P42: 2216.76 | Q42: =SUBTOTAL(109,I42:P42) -> 15230.8 | R42: 5.28 | S42: =COUNTIF(I42:P42,">0") -> 2 | T42: =Q42-R42 -> 15225.52 | U42: =IF(Q42=0,0,R42/Q42) -> 0.00034666597 | V42: {=_xlfn.IFS(S42=0,"Alta sin facturar",S42>2,"Cliente",S42>0,"Cliente nuevo")} -> Cliente nuevo | W42: =IF(T42<1,"Sin pago","Ha pagado") -> Ha pagado | AG42: Ejecutivo | AH42: (Todas)
A43: 44575 | B43: =PROPER(TEXT(A43,"mmmm")) -> Enero | C43: Iván Luna | D43: =VLOOKUP(Datos!$C43,$AQ$2:$AR$41,2,0) -> Norte | E43: 23121 | F43: {=_xlfn.IFS(H43=0,"Alta sin facturar",H43>2,"Cliente",H43>0,"Cliente nuevo")} -> Alta sin facturar | H43: =COUNTIF(I43:P43,">0") -> 0 | I43: 0 | J43: 0 | K43: 0 | L43: 0 | M43: 0 | N43: 0 | O43: 0 | P43: 0 | Q43: =SUBTOTAL(109,I43:P43) -> 0 | S43: =COUNTIF(I43:P43,">0") -> 0 | T43: =Q43-R43 -> 0 | U43: =IF(Q43=0,0,R43/Q43) -> 0 | V43: {=_xlfn.IFS(S43=0,"Alta sin facturar",S43>2,"Cliente",S43>0,"Cliente nuevo")} -> Alta sin facturar | W43: =IF(T43<1,"Sin pago","Ha pagado") -> Sin pago
A44: 44575 | B44: =PROPER(TEXT(A44,"mmmm")) -> Enero | C44: Ricardo Vidal | D44: =VLOOKUP(Datos!$C44,$AQ$2:$AR$41,2,0) -> Magallanes | E44: 23122 | F44: {=_xlfn.IFS(H44=0,"Alta sin facturar",H44>2,"Cliente",H44>0,"Cliente nuevo")} -> Alta sin facturar | H44: =COUNTIF(I44:P44,">0") -> 0 | I44: 0 | J44: 0 | K44: 0 | L44: 0 | M44: 0 | N44: 0 | O44: 0 | P44: 0 | Q44: =SUBTOTAL(109,I44:P44) -> 0 | R44: 556.8 | S44: =COUNTIF(I44:P44,">0") -> 0 | T44: =Q44-R44 -> -556.8 | U44: =IF(Q44=0,0,R44/Q44) -> 0 | V44: {=_xlfn.IFS(S44=0,"Alta sin facturar",S44>2,"Cliente",S44>0,"Cliente nuevo")} -> Alta sin facturar | W44: =IF(T44<1,"Sin pago","Ha pagado") -> Sin pago | AH44: Pago
A45: 44575 | B45: =PROPER(TEXT(A45,"mmmm")) -> Enero | C45: Christian Castellanos | D45: =VLOOKUP(Datos!$C45,$AQ$2:$AR$41,2,0) -> Norte | E45: 23123 | F45: {=_xlfn.IFS(H45=0,"Alta sin facturar",H45>2,"Cliente",H45>0,"Cliente nuevo")} -> Alta sin facturar | H45: =COUNTIF(I45:P45,">0") -> 0 | I45: 0 | J45: 0 | K45: 0 | L45: 0 | M45: 0 | N45: 0 | O45: 0 | P45: 0 | Q45: =SUBTOTAL(109,I45:P45) -> 0 | S45: =COUNTIF(I45:P45,">0") -> 0 | T45: =Q45-R45 -> 0 | U45: =IF(Q45=0,0,R45/Q45) -> 0 | V45: {=_xlfn.IFS(S45=0,"Alta sin facturar",S45>2,"Cliente",S45>0,"Cliente nuevo")} -> Alta sin facturar | W45: =IF(T45<1,"Sin pago","Ha pagado") -> Sin pago | AG45: Categoría | AH45: Enero | AI45: Febrero | AJ45: Marzo | AK45: Abril | AL45: Mayo | AM45: Junio | AN45: Total general
A46: 44575 | B46: =PROPER(TEXT(A46,"mmmm")) -> Enero | C46: Christian Castellanos | D46: =VLOOKUP(Datos!$C46,$AQ$2:$AR$41,2,0) -> Norte | E46: 23124 | F46: {=_xlfn.IFS(H46=0,"Alta sin facturar",H46>2,"Cliente",H46>0,"Cliente nuevo")} -> Alta sin facturar | H46: =COUNTIF(I46:P46,">0") -> 0 | I46: 0 | J46: 0 | K46: 0 | L46: 0 | M46: 0 | N46: 0 | O46: 0 | P46: 0 | Q46: =SUBTOTAL(109,I46:P46) -> 0 | S46: =COUNTIF(I46:P46,">0") -> 0 | T46: =Q46-R46 -> 0 | U46: =IF(Q46=0,0,R46/Q46) -> 0 | V46: {=_xlfn.IFS(S46=0,"Alta sin facturar",S46>2,"Cliente",S46>0,"Cliente nuevo")} -> Alta sin facturar | W46: =IF(T46<1,"Sin pago","Ha pagado") -> Sin pago | AG46: Cliente
A47: 44575 | B47: =PROPER(TEXT(A47,"mmmm")) -> Enero | C47: Christian Castellanos | D47: =VLOOKUP(Datos!$C47,$AQ$2:$AR$41,2,0) -> Norte | E47: 23125 | F47: {=_xlfn.IFS(H47=0,"Alta sin facturar",H47>2,"Cliente",H47>0,"Cliente nuevo")} -> Alta sin facturar | H47: =COUNTIF(I47:P47,">0") -> 0 | I47: 0 | J47: 0 | K47: 0 | L47: 0 | M47: 0 | N47: 0 | O47: 0 | P47: 0 | Q47: =SUBTOTAL(109,I47:P47) -> 0 | S47: =COUNTIF(I47:P47,">0") -> 0 | T47: =Q47-R47 -> 0 | U47: =IF(Q47=0,0,R47/Q47) -> 0 | V47: {=_xlfn.IFS(S47=0,"Alta sin facturar",S47>2,"Cliente",S47>0,"Cliente nuevo")} -> Alta sin facturar | W47: =IF(T47<1,"Sin pago","Ha pagado") -> Sin pago | AG47: Cliente nuevo
A48: 44575 | B48: =PROPER(TEXT(A48,"mmmm")) -> Enero | C48: Yuritzi Alejo | D48: =VLOOKUP(Datos!$C48,$AQ$2:$AR$41,2,0) -> Centro | E48: 23126 | F48: {=_xlfn.IFS(H48=0,"Alta sin facturar",H48>2,"Cliente",H48>0,"Cliente nuevo")} -> Alta sin facturar | H48: =COUNTIF(I48:P48,">0") -> 0 | I48: 0 | J48: 0 | K48: 0 | L48: 0 | M48: 0 | N48: 0 | O48: 0 | P48: 0 | Q48: =SUBTOTAL(109,I48:P48) -> 0 | S48: =COUNTIF(I48:P48,">0") -> 0 | T48: =Q48-R48 -> 0 | U48: =IF(Q48=0,0,R48/Q48) -> 0 | V48: {=_xlfn.IFS(S48=0,"Alta sin facturar",S48>2,"Cliente",S48>0,"Cliente nuevo")} -> Alta sin facturar | W48: =IF(T48<1,"Sin pago","Ha pagado") -> Sin pago | AG48: Total general
A49: 44575 | B49: =PROPER(TEXT(A49,"mmmm")) -> Enero | C49: Yuritzi Alejo | D49: =VLOOKUP(Datos!$C49,$AQ$2:$AR$41,2,0) -> Centro | E49: 23127 | F49: {=_xlfn.IFS(H49=0,"Alta sin facturar",H49>2,"Cliente",H49>0,"Cliente nuevo")} -> Alta sin facturar | H49: =COUNTIF(I49:P49,">0") -> 0 | I49: 0 | J49: 0 | K49: 0 | L49: 0 | M49: 0 | N49: 0 | O49: 0 | P49: 0 | Q49: =SUBTOTAL(109,I49:P49) -> 0 | R49: 0 | S49: =COUNTIF(I49:P49,">0") -> 0 | T49: =Q49-R49 -> 0 | U49: =IF(Q49=0,0,R49/Q49) -> 0 | V49: {=_xlfn.IFS(S49=0,"Alta sin facturar",S49>2,"Cliente",S49>0,"Cliente nuevo")} -> Alta sin facturar | W49: =IF(T49<1,"Sin pago","Ha pagado") -> Sin pago
A50: 44575 | B50: =PROPER(TEXT(A50,"mmmm")) -> Enero | C50: Julio César Trejo | D50: =VLOOKUP(Datos!$C50,$AQ$2:$AR$41,2,0) -> Norte | E50: 23128 | F50: {=_xlfn.IFS(H50=0,"Alta sin facturar",H50>2,"Cliente",H50>0,"Cliente nuevo")} -> Cliente nuevo | H50: =COUNTIF(I50:P50,">0") -> 1 | I50: 0 | J50: 214.6 | K50: 0 | L50: 0 | M50: 0 | N50: 0 | O50: 0 | P50: 0 | Q50: =SUBTOTAL(109,I50:P50) -> 214.6 | R50: 1484.8 | S50: =COUNTIF(I50:P50,">0") -> 1 | T50: =Q50-R50 -> -1270.2 | U50: =IF(Q50=0,0,R50/Q50) -> 6.9189189 | V50: {=_xlfn.IFS(S50=0,"Alta sin facturar",S50>2,"Cliente",S50>0,"Cliente nuevo")} -> Cliente nuevo | W50: =IF(T50<1,"Sin pago","Ha pagado") -> Sin pago | AH50: =Datos!AH56/(Datos!AH56+Datos!AH57) -> #DIV/0! | AI50: =IF(Datos!AI56=0,"",IFERROR(Datos!AI56&" - "&TEXT(Datos!AI56/(Datos!AI56+Datos!AI58),"0.0%"),""))
A51: 44575 | B51: =PROPER(TEXT(A51,"mmmm")) -> Enero | C51: Yuriana Argüello | D51: =VLOOKUP(Datos!$C51,$AQ$2:$AR$41,2,0) -> Centro | E51: 23129 | F51: {=_xlfn.IFS(H51=0,"Alta sin facturar",H51>2,"Cliente",H51>0,"Cliente nuevo")} -> Alta sin facturar | H51: =COUNTIF(I51:P51,">0") -> 0 | I51: 0 | J51: 0 | K51: 0 | L51: 0 | M51: 0 | N51: 0 | O51: 0 | P51: 0 | Q51: =SUBTOTAL(109,I51:P51) -> 0 | S51: =COUNTIF(I51:P51,">0") -> 0 | T51: =Q51-R51 -> 0 | U51: =IF(Q51=0,0,R51/Q51) -> 0 | V51: {=_xlfn.IFS(S51=0,"Alta sin facturar",S51>2,"Cliente",S51>0,"Cliente nuevo")} -> Alta sin facturar | W51: =IF(T51<1,"Sin pago","Ha pagado") -> Sin pago | AG51: Categoría de pago | AH51: Sin pago | AI51: =Datos!AI56/(Datos!AI56+Datos!AI57) -> #DIV/0!
A52: 44575 | B52: =PROPER(TEXT(A52,"mmmm")) -> Enero | C52: Best | D52: =VLOOKUP(Datos!$C52,$AQ$2:$AR$41,2,0) -> Centro | E52: 23130 | F52: {=_xlfn.IFS(H52=0,"Alta sin facturar",H52>2,"Cliente",H52>0,"Cliente nuevo")} -> Alta sin facturar | H52: =COUNTIF(I52:P52,">0") -> 0 | I52: 0 | J52: 0 | K52: 0 | L52: 0 | M52: 0 | N52: 0 | O52: 0 | P52: 0 | Q52: =SUBTOTAL(109,I52:P52) -> 0 | S52: =COUNTIF(I52:P52,">0") -> 0 | T52: =Q52-R52 -> 0 | U52: =IF(Q52=0,0,R52/Q52) -> 0 | V52: {=_xlfn.IFS(S52=0,"Alta sin facturar",S52>2,"Cliente",S52>0,"Cliente nuevo")} -> Alta sin facturar | W52: =IF(T52<1,"Sin pago","Ha pagado") -> Sin pago | AG52: Ejecutivo | AH52: (Varios elementos) | AI52: =Datos!AI57/(Datos!AI56+Datos!AI57) -> #DIV/0!
A53: 44575 | B53: =PROPER(TEXT(A53,"mmmm")) -> Enero | C53: Best | D53: =VLOOKUP(Datos!$C53,$AQ$2:$AR$41,2,0) -> Centro | E53: 23131 | F53: {=_xlfn.IFS(H53=0,"Alta sin facturar",H53>2,"Cliente",H53>0,"Cliente nuevo")} -> Alta sin facturar | H53: =COUNTIF(I53:P53,">0") -> 0 | I53: 0 | J53: 0 | K53: 0 | L53: 0 | M53: 0 | N53: 0 | O53: 0 | P53: 0 | Q53: =SUBTOTAL(109,I53:P53) -> 0 | S53: =COUNTIF(I53:P53,">0") -> 0 | T53: =Q53-R53 -> 0 | U53: =IF(Q53=0,0,R53/Q53) -> 0 | V53: {=_xlfn.IFS(S53=0,"Alta sin facturar",S53>2,"Cliente",S53>0,"Cliente nuevo")} -> Alta sin facturar | W53: =IF(T53<1,"Sin pago","Ha pagado") -> Sin pago | AI53: =Datos!AI57&" "&"- "&TEXT(Datos!AI57/(Datos!AI56+Datos!AI57),"0.00%") -> #DIV/0! | AJ53: =Datos!AJ57&" "&"- "&TEXT(Datos!AJ57/(Datos!AJ56+Datos!AJ57),"0.00%") -> #DIV/0! | AK53: =IF(Datos!AK57=0,"",IFERROR(Datos!AK57&" - "&TEXT(Datos!AK57/(Datos!AK57+Datos!AK37),"0.0%"),"")) | AL53: =IF(Datos!AL57=0,"",IFERROR(Datos!AL57&" - "&TEXT(Datos!AL57/(Datos!AL57+Datos!AL37),"0.0%"),"")) | AM53: =IF(Datos!AM57=0,"",IFERROR(Datos!AM57&" - "&TEXT(Datos!AM57/(Datos!AM57+Datos!AM37),"0.0%"),""))
A54: 44576 | B54: =PROPER(TEXT(A54,"mmmm")) -> Enero | C54: Christian Castellanos | D54: =VLOOKUP(Datos!$C54,$AQ$2:$AR$41,2,0) -> Norte | E54: 23132 | F54: {=_xlfn.IFS(H54=0,"Alta sin facturar",H54>2,"Cliente",H54>0,"Cliente nuevo")} -> Alta sin facturar | H54: =COUNTIF(I54:P54,">0") -> 0 | I54: 0 | J54: 0 | K54: 0 | L54: 0 | M54: 0 | N54: 0 | O54: 0 | P54: 0 | Q54: =SUBTOTAL(109,I54:P54) -> 0 | S54: =COUNTIF(I54:P54,">0") -> 0 | T54: =Q54-R54 -> 0 | U54: =IF(Q54=0,0,R54/Q54) -> 0 | V54: {=_xlfn.IFS(S54=0,"Alta sin facturar",S54>2,"Cliente",S54>0,"Cliente nuevo")} -> Alta sin facturar | W54: =IF(T54<1,"Sin pago","Ha pagado") -> Sin pago | AH54: Pago
A55: 44576 | B55: =PROPER(TEXT(A55,"mmmm")) -> Enero | C55: Christian Castellanos | D55: =VLOOKUP(Datos!$C55,$AQ$2:$AR$41,2,0) -> Norte | E55: 23133 | F55: {=_xlfn.IFS(H55=0,"Alta sin facturar",H55>2,"Cliente",H55>0,"Cliente nuevo")} -> Alta sin facturar | H55: =COUNTIF(I55:P55,">0") -> 0 | I55: 0 | J55: 0 | K55: 0 | L55: 0 | M55: 0 | N55: 0 | O55: 0 | P55: 0 | Q55: =SUBTOTAL(109,I55:P55) -> 0 | R55: 1624 | S55: =COUNTIF(I55:P55,">0") -> 0 | T55: =Q55-R55 -> -1624 | U55: =IF(Q55=0,0,R55/Q55) -> 0 | V55: {=_xlfn.IFS(S55=0,"Alta sin facturar",S55>2,"Cliente",S55>0,"Cliente nuevo")} -> Alta sin facturar | W55: =IF(T55<1,"Sin pago","Ha pagado") -> Sin pago | AG55: Categoría | AH55: Enero | AI55: Febrero | AJ55: Marzo | AK55: Abril | AL55: Mayo | AM55: Junio | AN55: Total general
A56: 44576 | B56: =PROPER(TEXT(A56,"mmmm")) -> Enero | C56: Yuriana Argüello | D56: =VLOOKUP(Datos!$C56,$AQ$2:$AR$41,2,0) -> Centro | E56: 23134 | F56: {=_xlfn.IFS(H56=0,"Alta sin facturar",H56>2,"Cliente",H56>0,"Cliente nuevo")} -> Alta sin facturar | H56: =COUNTIF(I56:P56,">0") -> 0 | I56: 0 | J56: 0 | K56: 0 | L56: 0 | M56: 0 | N56: 0 | O56: 0 | P56: 0 | Q56: =SUBTOTAL(109,I56:P56) -> 0 | S56: =COUNTIF(I56:P56,">0") -> 0 | T56: =Q56-R56 -> 0 | U56: =IF(Q56=0,0,R56/Q56) -> 0 | V56: {=_xlfn.IFS(S56=0,"Alta sin facturar",S56>2,"Cliente",S56>0,"Cliente nuevo")} -> Alta sin facturar | W56: =IF(T56<1,"Sin pago","Ha pagado") -> Sin pago | AG56: Cliente
A57: 44576 | B57: =PROPER(TEXT(A57,"mmmm")) -> Enero | C57: Yuriana Argüello | D57: =VLOOKUP(Datos!$C57,$AQ$2:$AR$41,2,0) -> Centro | E57: 23135 | F57: {=_xlfn.IFS(H57=0,"Alta sin facturar",H57>2,"Cliente",H57>0,"Cliente nuevo")} -> Alta sin facturar | H57: =COUNTIF(I57:P57,">0") -> 0 | I57: 0 | J57: 0 | K57: 0 | L57: 0 | M57: 0 | N57: 0 | O57: 0 | P57: 0 | Q57: =SUBTOTAL(109,I57:P57) -> 0 | S57: =COUNTIF(I57:P57,">0") -> 0 | T57: =Q57-R57 -> 0 | U57: =IF(Q57=0,0,R57/Q57) -> 0 | V57: {=_xlfn.IFS(S57=0,"Alta sin facturar",S57>2,"Cliente",S57>0,"Cliente nuevo")} -> Alta sin facturar | W57: =IF(T57<1,"Sin pago","Ha pagado") -> Sin pago | AG57: Cliente nuevo
A58: 44576 | B58: =PROPER(TEXT(A58,"mmmm")) -> Enero | C58: Christian Castellanos | D58: =VLOOKUP(Datos!$C58,$AQ$2:$AR$41,2,0) -> Norte | E58: 23136 | F58: {=_xlfn.IFS(H58=0,"Alta sin facturar",H58>2,"Cliente",H58>0,"Cliente nuevo")} -> Alta sin facturar | H58: =COUNTIF(I58:P58,">0") -> 0 | I58: 0 | J58: 0 | K58: 0 | L58: 0 | M58: 0 | N58: 0 | O58: 0 | P58: 0 | Q58: =SUBTOTAL(109,I58:P58) -> 0 | S58: =COUNTIF(I58:P58,">0") -> 0 | T58: =Q58-R58 -> 0 | U58: =IF(Q58=0,0,R58/Q58) -> 0 | V58: {=_xlfn.IFS(S58=0,"Alta sin facturar",S58>2,"Cliente",S58>0,"Cliente nuevo")} -> Alta sin facturar | W58: =IF(T58<1,"Sin pago","Ha pagado") -> Sin pago | AG58: Total general
A59: 44576 | B59: =PROPER(TEXT(A59,"mmmm")) -> Enero | C59: Christian Castellanos | D59: =VLOOKUP(Datos!$C59,$AQ$2:$AR$41,2,0) -> Norte | E59: 23137 | F59: {=_xlfn.IFS(H59=0,"Alta sin facturar",H59>2,"Cliente",H59>0,"Cliente nuevo")} -> Alta sin facturar | H59: =COUNTIF(I59:P59,">0") -> 0 | I59: 0 | J59: 0 | K59: 0 | L59: 0 | M59: 0 | N59: 0 | O59: 0 | P59: 0 | Q59: =SUBTOTAL(109,I59:P59) -> 0 | S59: =COUNTIF(I59:P59,">0") -> 0 | T59: =Q59-R59 -> 0 | U59: =IF(Q59=0,0,R59/Q59) -> 0 | V59: {=_xlfn.IFS(S59=0,"Alta sin facturar",S59>2,"Cliente",S59>0,"Cliente nuevo")} -> Alta sin facturar | W59: =IF(T59<1,"Sin pago","Ha pagado") -> Sin pago
A60: 44576 | B60: =PROPER(TEXT(A60,"mmmm")) -> Enero | C60: Christian Castellanos | D60: =VLOOKUP(Datos!$C60,$AQ$2:$AR$41,2,0) -> Norte | E60: 23138 | F60: {=_xlfn.IFS(H60=0,"Alta sin facturar",H60>2,"Cliente",H60>0,"Cliente nuevo")} -> Alta sin facturar | H60: =COUNTIF(I60:P60,">0") -> 0 | I60: 0 | J60: 0 | K60: 0 | L60: 0 | M60: 0 | N60: 0 | O60: 0 | P60: 0 | Q60: =SUBTOTAL(109,I60:P60) -> 0 | S60: =COUNTIF(I60:P60,">0") -> 0 | T60: =Q60-R60 -> 0 | U60: =IF(Q60=0,0,R60/Q60) -> 0 | V60: {=_xlfn.IFS(S60=0,"Alta sin facturar",S60>2,"Cliente",S60>0,"Cliente nuevo")} -> Alta sin facturar | W60: =IF(T60<1,"Sin pago","Ha pagado") -> Sin pago | AG60: Categoría de pago | AH60: Sin pago
A61: 44576 | B61: =PROPER(TEXT(A61,"mmmm")) -> Enero | C61: Dolores Jiménez | D61: =VLOOKUP(Datos!$C61,$AQ$2:$AR$41,2,0) -> Norte | E61: 23139 | F61: {=_xlfn.IFS(H61=0,"Alta sin facturar",H61>2,"Cliente",H61>0,"Cliente nuevo")} -> Cliente | H61: =COUNTIF(I61:P61,">0") -> 4 | I61: 0 | J61: 0 | K61: 0 | L61: 116 | M61: 0 | N61: 3589.04 | O61: 10073.44 | P61: 26403.92 | Q61: =SUBTOTAL(109,I61:P61) -> 40182.4 | R61: 3475.36 | S61: =COUNTIF(I61:P61,">0") -> 4 | T61: =Q61-R61 -> 36707.04 | U61: =IF(Q61=0,0,R61/Q61) -> 0.086489607 | V61: {=_xlfn.IFS(S61=0,"Alta sin facturar",S61>2,"Cliente",S61>0,"Cliente nuevo")} -> Cliente | W61: =IF(T61<1,"Sin pago","Ha pagado") -> Ha pagado | AG61: Ejecutivo | AH61: (Varios elementos)
A62: 44576 | B62: =PROPER(TEXT(A62,"mmmm")) -> Enero | C62: Alfredo Almaráz | D62: =VLOOKUP(Datos!$C62,$AQ$2:$AR$41,2,0) -> Magallanes | E62: 23140 | F62: {=_xlfn.IFS(H62=0,"Alta sin facturar",H62>2,"Cliente",H62>0,"Cliente nuevo")} -> Cliente nuevo | H62: =COUNTIF(I62:P62,">0") -> 2 | I62: 0 | J62: 0 | K62: 0 | L62: 0 | M62: 0 | N62: 14834.08 | O62: 0 | P62: 17024.16 | Q62: =SUBTOTAL(109,I62:P62) -> 31858.24 | R62: 18884.8 | S62: =COUNTIF(I62:P62,">0") -> 2 | T62: =Q62-R62 -> 12973.44 | U62: =IF(Q62=0,0,R62/Q62) -> 0.592776 | V62: {=_xlfn.IFS(S62=0,"Alta sin facturar",S62>2,"Cliente",S62>0,"Cliente nuevo")} -> Cliente nuevo | W62: =IF(T62<1,"Sin pago","Ha pagado") -> Ha pagado
A63: 44576 | B63: =PROPER(TEXT(A63,"mmmm")) -> Enero | C63: Alfredo Almaráz | D63: =VLOOKUP(Datos!$C63,$AQ$2:$AR$41,2,0) -> Magallanes | E63: 23141 | F63: {=_xlfn.IFS(H63=0,"Alta sin facturar",H63>2,"Cliente",H63>0,"Cliente nuevo")} -> Cliente nuevo | H63: =COUNTIF(I63:P63,">0") -> 2 | I63: 0 | J63: 0 | K63: 0 | L63: 0 | M63: 0 | N63: 1180.88 | O63: 0 | P63: 4040.28 | Q63: =SUBTOTAL(109,I63:P63) -> 5221.16 | R63: 685.56 | S63: =COUNTIF(I63:P63,">0") -> 2 | T63: =Q63-R63 -> 4535.6 | U63: =IF(Q63=0,0,R63/Q63) -> 0.13130415 | V63: {=_xlfn.IFS(S63=0,"Alta sin facturar",S63>2,"Cliente",S63>0,"Cliente nuevo")} -> Cliente nuevo | W63: =IF(T63<1,"Sin pago","Ha pagado") -> Ha pagado | AH63: Pago
A64: 44576 | B64: =PROPER(TEXT(A64,"mmmm")) -> Enero | C64: Yuriana Argüello | D64: =VLOOKUP(Datos!$C64,$AQ$2:$AR$41,2,0) -> Centro | E64: 23142 | F64: {=_xlfn.IFS(H64=0,"Alta sin facturar",H64>2,"Cliente",H64>0,"Cliente nuevo")} -> Cliente nuevo | H64: =COUNTIF(I64:P64,">0") -> 2 | I64: 0 | J64: 0 | K64: 3248 | L64: 3712 | M64: 0 | N64: 0 | O64: 0 | P64: 0 | Q64: =SUBTOTAL(109,I64:P64) -> 6960 | R64: 0 | S64: =COUNTIF(I64:P64,">0") -> 2 | T64: =Q64-R64 -> 6960 | U64: =IF(Q64=0,0,R64/Q64) -> 0 | V64: {=_xlfn.IFS(S64=0,"Alta sin facturar",S64>2,"Cliente",S64>0,"Cliente nuevo")} -> Cliente nuevo | W64: =IF(T64<1,"Sin pago","Ha pagado") -> Ha pagado | AG64: Categoría | AH64: Enero | AI64: Febrero | AJ64: Marzo | AK64: Abril | AL64: Mayo | AM64: Junio | AN64: Total general
A65: 44578 | B65: =PROPER(TEXT(A65,"mmmm")) -> Enero | C65: Alfredo Almaráz | D65: =VLOOKUP(Datos!$C65,$AQ$2:$AR$41,2,0) -> Magallanes | E65: 23143 | F65: {=_xlfn.IFS(H65=0,"Alta sin facturar",H65>2,"Cliente",H65>0,"Cliente nuevo")} -> Cliente nuevo | H65: =COUNTIF(I65:P65,">0") -> 1 | I65: 0 | J65: 0 | K65: 0 | L65: 0 | M65: 0 | N65: 6919.4 | O65: 0 | P65: 0 | Q65: =SUBTOTAL(109,I65:P65) -> 6919.4 | R65: 1318.6 | S65: =COUNTIF(I65:P65,">0") -> 1 | T65: =Q65-R65 -> 5600.8 | U65: =IF(Q65=0,0,R65/Q65) -> 0.19056566 | V65: {=_xlfn.IFS(S65=0,"Alta sin facturar",S65>2,"Cliente",S65>0,"Cliente nuevo")} -> Cliente nuevo | W65: =IF(T65<1,"Sin pago","Ha pagado") -> Ha pagado | AG65: Cliente
A66: 44578 | B66: =PROPER(TEXT(A66,"mmmm")) -> Enero | C66: Jose Carlos Orozco | D66: =VLOOKUP(Datos!$C66,$AQ$2:$AR$41,2,0) -> Centro | E66: 23144 | F66: {=_xlfn.IFS(H66=0,"Alta sin facturar",H66>2,"Cliente",H66>0,"Cliente nuevo")} -> Cliente | H66: =COUNTIF(I66:P66,">0") -> 4 | I66: 0 | J66: 580 | K66: 0 | L66: 0 | M66: 232 | N66: 7308 | O66: 232 | P66: 0 | Q66: =SUBTOTAL(109,I66:P66) -> 8352 | R66: 2436 | S66: =COUNTIF(I66:P66,">0") -> 4 | T66: =Q66-R66 -> 5916 | U66: =IF(Q66=0,0,R66/Q66) -> 0.29166667 | V66: {=_xlfn.IFS(S66=0,"Alta sin facturar",S66>2,"Cliente",S66>0,"Cliente nuevo")} -> Cliente | W66: =IF(T66<1,"Sin pago","Ha pagado") -> Ha pagado | AG66: Cliente nuevo
A67: 44578 | B67: =PROPER(TEXT(A67,"mmmm")) -> Enero | C67: Rubí Rodríguez | D67: =VLOOKUP(Datos!$C67,$AQ$2:$AR$41,2,0) -> Centro | E67: 23145 | F67: {=_xlfn.IFS(H67=0,"Alta sin facturar",H67>2,"Cliente",H67>0,"Cliente nuevo")} -> Cliente nuevo | H67: =COUNTIF(I67:P67,">0") -> 2 | I67: 0 | J67: 0 | K67: 1359.52 | L67: 247.08 | M67: 0 | N67: 0 | O67: 0 | P67: 0 | Q67: =SUBTOTAL(109,I67:P67) -> 1606.6 | R67: 3416.2 | S67: =COUNTIF(I67:P67,">0") -> 2 | T67: =Q67-R67 -> -1809.6 | U67: =IF(Q67=0,0,R67/Q67) -> 2.1263538 | V67: {=_xlfn.IFS(S67=0,"Alta sin facturar",S67>2,"Cliente",S67>0,"Cliente nuevo")} -> Cliente nuevo | W67: =IF(T67<1,"Sin pago","Ha pagado") -> Sin pago | AG67: Total general
A68: 44578 | B68: =PROPER(TEXT(A68,"mmmm")) -> Enero | C68: Yuritzi Alejo | D68: =VLOOKUP(Datos!$C68,$AQ$2:$AR$41,2,0) -> Centro | E68: 23146 | F68: {=_xlfn.IFS(H68=0,"Alta sin facturar",H68>2,"Cliente",H68>0,"Cliente nuevo")} -> Cliente | H68: =COUNTIF(I68:P68,">0") -> 7 | I68: 11137.16 | J68: 5568 | K68: 2784 | L68: 928 | M68: 0 | N68: 5568 | O68: 6844 | P68: 2784 | Q68: =SUBTOTAL(109,I68:P68) -> 35613.16 | R68: 1624 | S68: =COUNTIF(I68:P68,">0") -> 7 | T68: =Q68-R68 -> 33989.16 | U68: =IF(Q68=0,0,R68/Q68) -> 0.04560112 | V68: {=_xlfn.IFS(S68=0,"Alta sin facturar",S68>2,"Cliente",S68>0,"Cliente nuevo")} -> Cliente | W68: =IF(T68<1,"Sin pago","Ha pagado") -> Ha pagado
A69: 44578 | B69: =PROPER(TEXT(A69,"mmmm")) -> Enero | C69: Diana Tejadilla | D69: =VLOOKUP(Datos!$C69,$AQ$2:$AR$41,2,0) -> Centro | E69: 23147 | F69: {=_xlfn.IFS(H69=0,"Alta sin facturar",H69>2,"Cliente",H69>0,"Cliente nuevo")} -> Cliente | H69: =COUNTIF(I69:P69,">0") -> 5 | I69: 0 | J69: 0 | K69: 6296.48 | L69: 9632.64 | M69: 10268.32 | N69: 5230.44 | O69: 8150.16 | P69: 0 | Q69: =SUBTOTAL(109,I69:P69) -> 39578.04 | R69: 5945 | S69: =COUNTIF(I69:P69,">0") -> 5 | T69: =Q69-R69 -> 33633.04 | U69: =IF(Q69=0,0,R69/Q69) -> 0.15020956 | V69: {=_xlfn.IFS(S69=0,"Alta sin facturar",S69>2,"Cliente",S69>0,"Cliente nuevo")} -> Cliente | W69: =IF(T69<1,"Sin pago","Ha pagado") -> Ha pagado
A70: 44578 | B70: =PROPER(TEXT(A70,"mmmm")) -> Enero | C70: Diana Tejadilla | D70: =VLOOKUP(Datos!$C70,$AQ$2:$AR$41,2,0) -> Centro | E70: 23148 | F70: {=_xlfn.IFS(H70=0,"Alta sin facturar",H70>2,"Cliente",H70>0,"Cliente nuevo")} -> Alta sin facturar | H70: =COUNTIF(I70:P70,">0") -> 0 | I70: 0 | J70: 0 | K70: 0 | L70: 0 | M70: 0 | N70: 0 | O70: 0 | P70: 0 | Q70: =SUBTOTAL(109,I70:P70) -> 0 | S70: =COUNTIF(I70:P70,">0") -> 0 | T70: =Q70-R70 -> 0 | U70: =IF(Q70=0,0,R70/Q70) -> 0 | V70: {=_xlfn.IFS(S70=0,"Alta sin facturar",S70>2,"Cliente",S70>0,"Cliente nuevo")} -> Alta sin facturar | W70: =IF(T70<1,"Sin pago","Ha pagado") -> Sin pago | AG70: Categoría de pago | AH70: Sin pago
A71: 44578 | B71: =PROPER(TEXT(A71,"mmmm")) -> Enero | C71: Sandra Escoto | D71: =VLOOKUP(Datos!$C71,$AQ$2:$AR$41,2,0) -> Centro | E71: 23149 | F71: {=_xlfn.IFS(H71=0,"Alta sin facturar",H71>2,"Cliente",H71>0,"Cliente nuevo")} -> Alta sin facturar | H71: =COUNTIF(I71:P71,">0") -> 0 | I71: 0 | J71: 0 | K71: 0 | L71: 0 | M71: 0 | N71: 0 | O71: 0 | P71: 0 | Q71: =SUBTOTAL(109,I71:P71) -> 0 | S71: =COUNTIF(I71:P71,">0") -> 0 | T71: =Q71-R71 -> 0 | U71: =IF(Q71=0,0,R71/Q71) -> 0 | V71: {=_xlfn.IFS(S71=0,"Alta sin facturar",S71>2,"Cliente",S71>0,"Cliente nuevo")} -> Alta sin facturar | W71: =IF(T71<1,"Sin pago","Ha pagado") -> Sin pago | AG71: Ejecutivo | AH71: (Varios elementos)
A72: 44578 | B72: =PROPER(TEXT(A72,"mmmm")) -> Enero | C72: Sandra Escoto | D72: =VLOOKUP(Datos!$C72,$AQ$2:$AR$41,2,0) -> Centro | E72: 23150 | F72: {=_xlfn.IFS(H72=0,"Alta sin facturar",H72>2,"Cliente",H72>0,"Cliente nuevo")} -> Alta sin facturar | H72: =COUNTIF(I72:P72,">0") -> 0 | I72: 0 | J72: 0 | K72: 0 | L72: 0 | M72: 0 | N72: 0 | O72: 0 | P72: 0 | Q72: =SUBTOTAL(109,I72:P72) -> 0 | S72: =COUNTIF(I72:P72,">0") -> 0 | T72: =Q72-R72 -> 0 | U72: =IF(Q72=0,0,R72/Q72) -> 0 | V72: {=_xlfn.IFS(S72=0,"Alta sin facturar",S72>2,"Cliente",S72>0,"Cliente nuevo")} -> Alta sin facturar | W72: =IF(T72<1,"Sin pago","Ha pagado") -> Sin pago
A73: 44578 | B73: =PROPER(TEXT(A73,"mmmm")) -> Enero | C73: Alfredo Almaráz | D73: =VLOOKUP(Datos!$C73,$AQ$2:$AR$41,2,0) -> Magallanes | E73: 23151 | F73: {=_xlfn.IFS(H73=0,"Alta sin facturar",H73>2,"Cliente",H73>0,"Cliente nuevo")} -> Cliente nuevo | H73: =COUNTIF(I73:P73,">0") -> 2 | I73: 0 | J73: 0 | K73: 0 | L73: 0 | M73: 0 | N73: 8111.88 | O73: 0 | P73: 13553.44 | Q73: =SUBTOTAL(109,I73:P73) -> 21665.32 | R73: 3526.4 | S73: =COUNTIF(I73:P73,">0") -> 2 | T73: =Q73-R73 -> 18138.92 | U73: =IF(Q73=0,0,R73/Q73) -> 0.16276704 | V73: {=_xlfn.IFS(S73=0,"Alta sin facturar",S73>2,"Cliente",S73>0,"Cliente nuevo")} -> Cliente nuevo | W73: =IF(T73<1,"Sin pago","Ha pagado") -> Ha pagado | AH73: Etiquetas de columna
A74: 44579 | B74: =PROPER(TEXT(A74,"mmmm")) -> Enero | C74: Marcos López | D74: =VLOOKUP(Datos!$C74,$AQ$2:$AR$41,2,0) -> Sur | E74: 23152 | F74: {=_xlfn.IFS(H74=0,"Alta sin facturar",H74>2,"Cliente",H74>0,"Cliente nuevo")} -> Alta sin facturar | H74: =COUNTIF(I74:P74,">0") -> 0 | I74: 0 | J74: 0 | K74: 0 | L74: 0 | M74: 0 | N74: 0 | O74: 0 | P74: 0 | Q74: =SUBTOTAL(109,I74:P74) -> 0 | S74: =COUNTIF(I74:P74,">0") -> 0 | T74: =Q74-R74 -> 0 | U74: =IF(Q74=0,0,R74/Q74) -> 0 | V74: {=_xlfn.IFS(S74=0,"Alta sin facturar",S74>2,"Cliente",S74>0,"Cliente nuevo")} -> Alta sin facturar | W74: =IF(T74<1,"Sin pago","Ha pagado") -> Sin pago | AH74: Alta sin facturar | AI74: Cliente | AJ74: Cliente nuevo
A75: 44579 | B75: =PROPER(TEXT(A75,"mmmm")) -> Enero | C75: Marcos López | D75: =VLOOKUP(Datos!$C75,$AQ$2:$AR$41,2,0) -> Sur | E75: 23153 | F75: {=_xlfn.IFS(H75=0,"Alta sin facturar",H75>2,"Cliente",H75>0,"Cliente nuevo")} -> Alta sin facturar | H75: =COUNTIF(I75:P75,">0") -> 0 | I75: 0 | J75: 0 | K75: 0 | L75: 0 | M75: 0 | N75: 0 | O75: 0 | P75: 0 | Q75: =SUBTOTAL(109,I75:P75) -> 0 | R75: 0 | S75: =COUNTIF(I75:P75,">0") -> 0 | T75: =Q75-R75 -> 0 | U75: =IF(Q75=0,0,R75/Q75) -> 0 | V75: {=_xlfn.IFS(S75=0,"Alta sin facturar",S75>2,"Cliente",S75>0,"Cliente nuevo")} -> Alta sin facturar | W75: =IF(T75<1,"Sin pago","Ha pagado") -> Sin pago | AG75: Suma de Saldo Junio
A76: 44579 | B76: =PROPER(TEXT(A76,"mmmm")) -> Enero | C76: Alfredo Almaráz | D76: =VLOOKUP(Datos!$C76,$AQ$2:$AR$41,2,0) -> Magallanes | E76: 23154 | F76: {=_xlfn.IFS(H76=0,"Alta sin facturar",H76>2,"Cliente",H76>0,"Cliente nuevo")} -> Cliente | H76: =COUNTIF(I76:P76,">0") -> 8 | I76: 1643.72 | J76: 1966.2 | K76: 5735.04 | L76: 3177.24 | M76: 3874.4 | N76: 2753.84 | O76: 1780.6 | P76: 3858.16 | Q76: =SUBTOTAL(109,I76:P76) -> 24789.2 | R76: 389.76 | S76: =COUNTIF(I76:P76,">0") -> 8 | T76: =Q76-R76 -> 24399.44 | U76: =IF(Q76=0,0,R76/Q76) -> 0.015722976 | V76: {=_xlfn.IFS(S76=0,"Alta sin facturar",S76>2,"Cliente",S76>0,"Cliente nuevo")} -> Cliente | W76: =IF(T76<1,"Sin pago","Ha pagado") -> Ha pagado
A77: 44579 | B77: =PROPER(TEXT(A77,"mmmm")) -> Enero | C77: Noe Acevedo | D77: =VLOOKUP(Datos!$C77,$AQ$2:$AR$41,2,0) -> Norte | E77: 23155 | F77: {=_xlfn.IFS(H77=0,"Alta sin facturar",H77>2,"Cliente",H77>0,"Cliente nuevo")} -> Cliente | H77: =COUNTIF(I77:P77,">0") -> 8 | I77: 1392 | J77: 5990.24 | K77: 8325.32 | L77: 15277.2 | M77: 14458.24 | N77: 20869.56 | O77: 12753.04 | P77: 8781.2 | Q77: =SUBTOTAL(109,I77:P77) -> 87846.8 | R77: 4692.2 | S77: =COUNTIF(I77:P77,">0") -> 8 | T77: =Q77-R77 -> 83154.6 | U77: =IF(Q77=0,0,R77/Q77) -> 0.053413442 | V77: {=_xlfn.IFS(S77=0,"Alta sin facturar",S77>2,"Cliente",S77>0,"Cliente nuevo")} -> Cliente | W77: =IF(T77<1,"Sin pago","Ha pagado") -> Ha pagado
A78: 44579 | B78: =PROPER(TEXT(A78,"mmmm")) -> Enero | C78: Rubí Rodríguez | D78: =VLOOKUP(Datos!$C78,$AQ$2:$AR$41,2,0) -> Centro | E78: 23156 | F78: {=_xlfn.IFS(H78=0,"Alta sin facturar",H78>2,"Cliente",H78>0,"Cliente nuevo")} -> Cliente nuevo | H78: =COUNTIF(I78:P78,">0") -> 1 | I78: 0 | J78: 0 | K78: 0 | L78: 0 | M78: 0 | N78: 5800 | O78: 0 | P78: 0 | Q78: =SUBTOTAL(109,I78:P78) -> 5800 | R78: 5800 | S78: =COUNTIF(I78:P78,">0") -> 1 | T78: =Q78-R78 -> 0 | U78: =IF(Q78=0,0,R78/Q78) -> 1 | V78: {=_xlfn.IFS(S78=0,"Alta sin facturar",S78>2,"Cliente",S78>0,"Cliente nuevo")} -> Cliente nuevo | W78: =IF(T78<1,"Sin pago","Ha pagado") -> Sin pago
A79: 44579 | B79: =PROPER(TEXT(A79,"mmmm")) -> Enero | C79: Yuriana Argüello | D79: =VLOOKUP(Datos!$C79,$AQ$2:$AR$41,2,0) -> Centro | E79: 23157 | F79: {=_xlfn.IFS(H79=0,"Alta sin facturar",H79>2,"Cliente",H79>0,"Cliente nuevo")} -> Alta sin facturar | H79: =COUNTIF(I79:P79,">0") -> 0 | I79: 0 | J79: 0 | K79: 0 | L79: 0 | M79: 0 | N79: 0 | O79: 0 | P79: 0 | Q79: =SUBTOTAL(109,I79:P79) -> 0 | R79: 0 | S79: =COUNTIF(I79:P79,">0") -> 0 | T79: =Q79-R79 -> 0 | U79: =IF(Q79=0,0,R79/Q79) -> 0 | V79: {=_xlfn.IFS(S79=0,"Alta sin facturar",S79>2,"Cliente",S79>0,"Cliente nuevo")} -> Alta sin facturar | W79: =IF(T79<1,"Sin pago","Ha pagado") -> Sin pago
A80: 44579 | B80: =PROPER(TEXT(A80,"mmmm")) -> Enero | C80: Sandra Escoto | D80: =VLOOKUP(Datos!$C80,$AQ$2:$AR$41,2,0) -> Centro | E80: 23158 | F80: {=_xlfn.IFS(H80=0,"Alta sin facturar",H80>2,"Cliente",H80>0,"Cliente nuevo")} -> Cliente | H80: =COUNTIF(I80:P80,">0") -> 5 | I80: 0 | J80: 0 | K80: 0 | L80: 870 | M80: 5220 | N80: 24302 | O80: 9860 | P80: 16240 | Q80: =SUBTOTAL(109,I80:P80) -> 56492 | R80: 66352 | S80: =COUNTIF(I80:P80,">0") -> 5 | T80: =Q80-R80 -> -9860 | U80: =IF(Q80=0,0,R80/Q80) -> 1.174538 | V80: {=_xlfn.IFS(S80=0,"Alta sin facturar",S80>2,"Cliente",S80>0,"Cliente nuevo")} -> Cliente | W80: =IF(T80<1,"Sin pago","Ha pagado") -> Sin pago | AH80: Enero | AI80: Febrero | AJ80: Marzo | AK80: Abril | AL80: Mayo | AM80: Junio | AN80: Total
A81: 44580 | B81: =PROPER(TEXT(A81,"mmmm")) -> Enero | C81: Sandra Escoto | D81: =VLOOKUP(Datos!$C81,$AQ$2:$AR$41,2,0) -> Centro | E81: 23159 | F81: {=_xlfn.IFS(H81=0,"Alta sin facturar",H81>2,"Cliente",H81>0,"Cliente nuevo")} -> Cliente | H81: =COUNTIF(I81:P81,">0") -> 8 | I81: 78.88 | J81: 1122.88 | K81: 105.56 | L81: 66.12 | M81: 1517.28 | N81: 3485.8 | O81: 7553.92 | P81: 8539.92 | Q81: =SUBTOTAL(109,I81:P81) -> 22470.36 | R81: 6439.16 | S81: =COUNTIF(I81:P81,">0") -> 8 | T81: =Q81-R81 -> 16031.2 | U81: =IF(Q81=0,0,R81/Q81) -> 0.28656239 | V81: {=_xlfn.IFS(S81=0,"Alta sin facturar",S81>2,"Cliente",S81>0,"Cliente nuevo")} -> Cliente | W81: =IF(T81<1,"Sin pago","Ha pagado") -> Ha pagado | AG81: Cliente | AH81: 1809.6 | AI81: 0 | AJ81: 1359.52 | AK81: 247.08 | AL81: 0 | AM81: 0 | AN81: =SUM(AH81:AM81) -> 3416.2
A82: 44580 | B82: =PROPER(TEXT(A82,"mmmm")) -> Enero | C82: Julio César Trejo | D82: =VLOOKUP(Datos!$C82,$AQ$2:$AR$41,2,0) -> Norte | E82: 23160 | F82: {=_xlfn.IFS(H82=0,"Alta sin facturar",H82>2,"Cliente",H82>0,"Cliente nuevo")} -> Cliente nuevo | H82: =COUNTIF(I82:P82,">0") -> 1 | I82: 0 | J82: 0 | K82: 0 | L82: 116 | M82: 0 | N82: 0 | O82: 0 | P82: 0 | Q82: =SUBTOTAL(109,I82:P82) -> 116 | R82: 116 | S82: =COUNTIF(I82:P82,">0") -> 1 | T82: =Q82-R82 -> 0 | U82: =IF(Q82=0,0,R82/Q82) -> 1 | V82: {=_xlfn.IFS(S82=0,"Alta sin facturar",S82>2,"Cliente",S82>0,"Cliente nuevo")} -> Cliente nuevo | W82: =IF(T82<1,"Sin pago","Ha pagado") -> Sin pago | AG82: Cliente nuevo | AH82: 23545.68 | AI82: 11870.28 | AJ82: 12653.28 | AK82: 7027.28 | AL82: 57713.23 | AM82: 61696.92 | AN82: =SUM(AH82:AM82) -> 174506.67
A83: 44580 | B83: =PROPER(TEXT(A83,"mmmm")) -> Enero | C83: Christian Castellanos | D83: =VLOOKUP(Datos!$C83,$AQ$2:$AR$41,2,0) -> Norte | E83: 23161 | F83: {=_xlfn.IFS(H83=0,"Alta sin facturar",H83>2,"Cliente",H83>0,"Cliente nuevo")} -> Alta sin facturar | H83: =COUNTIF(I83:P83,">0") -> 0 | I83: 0 | J83: 0 | K83: 0 | L83: 0 | M83: 0 | N83: 0 | O83: 0 | P83: 0 | Q83: =SUBTOTAL(109,I83:P83) -> 0 | S83: =COUNTIF(I83:P83,">0") -> 0 | T83: =Q83-R83 -> 0 | U83: =IF(Q83=0,0,R83/Q83) -> 0 | V83: {=_xlfn.IFS(S83=0,"Alta sin facturar",S83>2,"Cliente",S83>0,"Cliente nuevo")} -> Alta sin facturar | W83: =IF(T83<1,"Sin pago","Ha pagado") -> Sin pago | AH83: =SUM(AH81:AH82) -> 25355.28 | AI83: =SUM(AI81:AI82) -> 11870.28 | AJ83: =SUM(AJ81:AJ82) -> 14012.8 | AK83: =SUM(AK81:AK82) -> 7274.36 | AL83: =SUM(AL81:AL82) -> 57713.23 | AM83: =SUM(AM81:AM82) -> 61696.92 | AN83: =SUM(AN81:AN82) -> 177922.87
A84: 44580 | B84: =PROPER(TEXT(A84,"mmmm")) -> Enero | C84: Noe Acevedo | D84: =VLOOKUP(Datos!$C84,$AQ$2:$AR$41,2,0) -> Norte | E84: 23162 | F84: {=_xlfn.IFS(H84=0,"Alta sin facturar",H84>2,"Cliente",H84>0,"Cliente nuevo")} -> Cliente | H84: =COUNTIF(I84:P84,">0") -> 8 | I84: 324.8 | J84: 1231.92 | K84: 2019.56 | L84: 2323.48 | M84: 2730.64 | N84: 3636.6 | O84: 4003.16 | P84: 7189.68 | Q84: =SUBTOTAL(109,I84:P84) -> 23459.84 | R84: 0 | S84: =COUNTIF(I84:P84,">0") -> 8 | T84: =Q84-R84 -> 23459.84 | U84: =IF(Q84=0,0,R84/Q84) -> 0 | V84: {=_xlfn.IFS(S84=0,"Alta sin facturar",S84>2,"Cliente",S84>0,"Cliente nuevo")} -> Cliente | W84: =IF(T84<1,"Sin pago","Ha pagado") -> Ha pagado
A85: 44580 | B85: =PROPER(TEXT(A85,"mmmm")) -> Enero | C85: Christian Castellanos | D85: =VLOOKUP(Datos!$C85,$AQ$2:$AR$41,2,0) -> Norte | E85: 23163 | F85: {=_xlfn.IFS(H85=0,"Alta sin facturar",H85>2,"Cliente",H85>0,"Cliente nuevo")} -> Alta sin facturar | H85: =COUNTIF(I85:P85,">0") -> 0 | I85: 0 | J85: 0 | K85: 0 | L85: 0 | M85: 0 | N85: 0 | O85: 0 | P85: 0 | Q85: =SUBTOTAL(109,I85:P85) -> 0 | S85: =COUNTIF(I85:P85,">0") -> 0 | T85: =Q85-R85 -> 0 | U85: =IF(Q85=0,0,R85/Q85) -> 0 | V85: {=_xlfn.IFS(S85=0,"Alta sin facturar",S85>2,"Cliente",S85>0,"Cliente nuevo")} -> Alta sin facturar | W85: =IF(T85<1,"Sin pago","Ha pagado") -> Sin pago
A86: 44580 | B86: =PROPER(TEXT(A86,"mmmm")) -> Enero | C86: Genaro Castro | D86: =VLOOKUP(Datos!$C86,$AQ$2:$AR$41,2,0) -> Sur | E86: 23164 | F86: {=_xlfn.IFS(H86=0,"Alta sin facturar",H86>2,"Cliente",H86>0,"Cliente nuevo")} -> Cliente nuevo | H86: =COUNTIF(I86:P86,">0") -> 2 | I86: 0 | J86: 0 | K86: 0 | L86: 0 | M86: 0 | N86: 5635.28 | O86: 0 | P86: 2555.48 | Q86: =SUBTOTAL(109,I86:P86) -> 8190.76 | R86: 5754.76 | S86: =COUNTIF(I86:P86,">0") -> 2 | T86: =Q86-R86 -> 2436 | U86: =IF(Q86=0,0,R86/Q86) -> 0.7025917 | V86: {=_xlfn.IFS(S86=0,"Alta sin facturar",S86>2,"Cliente",S86>0,"Cliente nuevo")} -> Cliente nuevo | W86: =IF(T86<1,"Sin pago","Ha pagado") -> Ha pagado
A87: 44581 | B87: =PROPER(TEXT(A87,"mmmm")) -> Enero | C87: Rubí Rodríguez | D87: =VLOOKUP(Datos!$C87,$AQ$2:$AR$41,2,0) -> Centro | E87: 23165 | F87: {=_xlfn.IFS(H87=0,"Alta sin facturar",H87>2,"Cliente",H87>0,"Cliente nuevo")} -> Cliente | H87: =COUNTIF(I87:P87,">0") -> 5 | I87: 3.48 | J87: 9.28 | K87: 0 | L87: 6960 | M87: 0 | N87: 37700 | O87: 0 | P87: 868.84 | Q87: =SUBTOTAL(109,I87:P87) -> 45541.6 | R87: 28304 | S87: =COUNTIF(I87:P87,">0") -> 5 | T87: =Q87-R87 -> 17237.6 | U87: =IF(Q87=0,0,R87/Q87) -> 0.62149771 | V87: {=_xlfn.IFS(S87=0,"Alta sin facturar",S87>2,"Cliente",S87>0,"Cliente nuevo")} -> Cliente | W87: =IF(T87<1,"Sin pago","Ha pagado") -> Ha pagado
A88: 44581 | B88: =PROPER(TEXT(A88,"mmmm")) -> Enero | C88: Jose Carlos Orozco | D88: =VLOOKUP(Datos!$C88,$AQ$2:$AR$41,2,0) -> Centro | E88: 23166 | F88: {=_xlfn.IFS(H88=0,"Alta sin facturar",H88>2,"Cliente",H88>0,"Cliente nuevo")} -> Cliente | H88: =COUNTIF(I88:P88,">0") -> 4 | I88: 0 | J88: 127.6 | K88: 0 | L88: 0 | M88: 0 | N88: 14290.04 | O88: 881.6 | P88: 6845.16 | Q88: =SUBTOTAL(109,I88:P88) -> 22144.4 | R88: 0 | S88: =COUNTIF(I88:P88,">0") -> 4 | T88: =Q88-R88 -> 22144.4 | U88: =IF(Q88=0,0,R88/Q88) -> 0 | V88: {=_xlfn.IFS(S88=0,"Alta sin facturar",S88>2,"Cliente",S88>0,"Cliente nuevo")} -> Cliente | W88: =IF(T88<1,"Sin pago","Ha pagado") -> Ha pagado
A89: 44581 | B89: =PROPER(TEXT(A89,"mmmm")) -> Enero | C89: Christian Castellanos | D89: =VLOOKUP(Datos!$C89,$AQ$2:$AR$41,2,0) -> Norte | E89: 23167 | F89: {=_xlfn.IFS(H89=0,"Alta sin facturar",H89>2,"Cliente",H89>0,"Cliente nuevo")} -> Alta sin facturar | H89: =COUNTIF(I89:P89,">0") -> 0 | I89: 0 | J89: 0 | K89: 0 | L89: 0 | M89: 0 | N89: 0 | O89: 0 | P89: 0 | Q89: =SUBTOTAL(109,I89:P89) -> 0 | S89: =COUNTIF(I89:P89,">0") -> 0 | T89: =Q89-R89 -> 0 | U89: =IF(Q89=0,0,R89/Q89) -> 0 | V89: {=_xlfn.IFS(S89=0,"Alta sin facturar",S89>2,"Cliente",S89>0,"Cliente nuevo")} -> Alta sin facturar | W89: =IF(T89<1,"Sin pago","Ha pagado") -> Sin pago | AH89: Etiquetas de columna
A90: 44582 | B90: =PROPER(TEXT(A90,"mmmm")) -> Enero | C90: Rubí Rodríguez | D90: =VLOOKUP(Datos!$C90,$AQ$2:$AR$41,2,0) -> Centro | E90: 23168 | F90: {=_xlfn.IFS(H90=0,"Alta sin facturar",H90>2,"Cliente",H90>0,"Cliente nuevo")} -> Cliente | H90: =COUNTIF(I90:P90,">0") -> 6 | I90: 1193.64 | J90: 671.64 | K90: 3731.72 | L90: 925.68 | M90: 814.32 | N90: 15864.16 | O90: 0 | P90: 0 | Q90: =SUBTOTAL(109,I90:P90) -> 23201.16 | R90: 16681.44 | S90: =COUNTIF(I90:P90,">0") -> 6 | T90: =Q90-R90 -> 6519.72 | U90: =IF(Q90=0,0,R90/Q90) -> 0.71899164 | V90: {=_xlfn.IFS(S90=0,"Alta sin facturar",S90>2,"Cliente",S90>0,"Cliente nuevo")} -> Cliente | W90: =IF(T90<1,"Sin pago","Ha pagado") -> Ha pagado | AH90: Enero | AI90: Febrero | AJ90: Marzo | AK90: Abril | AL90: Mayo | AM90: Junio | AN90: Julio | AO90: Total general
A91: 44582 | B91: =PROPER(TEXT(A91,"mmmm")) -> Enero | C91: Yuritzi Alejo | D91: =VLOOKUP(Datos!$C91,$AQ$2:$AR$41,2,0) -> Centro | E91: 23169 | F91: {=_xlfn.IFS(H91=0,"Alta sin facturar",H91>2,"Cliente",H91>0,"Cliente nuevo")} -> Cliente | H91: =COUNTIF(I91:P91,">0") -> 8 | I91: 468.64 | J91: 8683.76 | K91: 5373.12 | L91: 17345.48 | M91: 22040 | N91: 4290.84 | O91: 512.72 | P91: 2488.2 | Q91: =SUBTOTAL(109,I91:P91) -> 61202.76 | R91: 512.72 | S91: =COUNTIF(I91:P91,">0") -> 8 | T91: =Q91-R91 -> 60690.04 | U91: =IF(Q91=0,0,R91/Q91) -> 0.0083774 | V91: {=_xlfn.IFS(S91=0,"Alta sin facturar",S91>2,"Cliente",S91>0,"Cliente nuevo")} -> Cliente | W91: =IF(T91<1,"Sin pago","Ha pagado") -> Ha pagado | AG91: Suma de Suma de ventas | AH91: 4455730.5 | AI91: 1062906.8 | AJ91: 1063635.3 | AK91: 1044391.3 | AL91: 809896.92 | AM91: 654291.04 | AN91: 251399.84 | AO91: 9342251.8
A92: 44582 | B92: =PROPER(TEXT(A92,"mmmm")) -> Enero | C92: Sandra Escoto | D92: =VLOOKUP(Datos!$C92,$AQ$2:$AR$41,2,0) -> Centro | E92: 23170 | F92: {=_xlfn.IFS(H92=0,"Alta sin facturar",H92>2,"Cliente",H92>0,"Cliente nuevo")} -> Cliente | H92: =COUNTIF(I92:P92,">0") -> 3 | I92: 0 | J92: 0 | K92: 0 | L92: 1023.12 | M92: 348 | N92: 1856 | O92: 0 | P92: 0 | Q92: =SUBTOTAL(109,I92:P92) -> 3227.12 | R92: 1376 | S92: =COUNTIF(I92:P92,">0") -> 3 | T92: =Q92-R92 -> 1851.12 | U92: =IF(Q92=0,0,R92/Q92) -> 0.42638638 | V92: {=_xlfn.IFS(S92=0,"Alta sin facturar",S92>2,"Cliente",S92>0,"Cliente nuevo")} -> Cliente | W92: =IF(T92<1,"Sin pago","Ha pagado") -> Ha pagado
A93: 44582 | B93: =PROPER(TEXT(A93,"mmmm")) -> Enero | C93: Cancelada | D93: =VLOOKUP(Datos!$C93,$AQ$2:$AR$41,2,0) -> #N/A | E93: 23171 | F93: {=_xlfn.IFS(H93=0,"Alta sin facturar",H93>2,"Cliente",H93>0,"Cliente nuevo")} -> Alta sin facturar | H93: =COUNTIF(I93:P93,">0") -> 0 | I93: 0 | J93: 0 | K93: 0 | L93: 0 | M93: 0 | N93: 0 | O93: 0 | P93: 0 | Q93: =SUBTOTAL(109,I93:P93) -> 0 | S93: =COUNTIF(I93:P93,">0") -> 0 | T93: =Q93-R93 -> 0 | U93: =IF(Q93=0,0,R93/Q93) -> 0 | V93: {=_xlfn.IFS(S93=0,"Alta sin facturar",S93>2,"Cliente",S93>0,"Cliente nuevo")} -> Alta sin facturar | W93: =IF(T93<1,"Sin pago","Ha pagado") -> Sin pago
A94: 44582 | B94: =PROPER(TEXT(A94,"mmmm")) -> Enero | C94: Christian Castellanos | D94: =VLOOKUP(Datos!$C94,$AQ$2:$AR$41,2,0) -> Norte | E94: 23172 | F94: {=_xlfn.IFS(H94=0,"Alta sin facturar",H94>2,"Cliente",H94>0,"Cliente nuevo")} -> Cliente | H94: =COUNTIF(I94:P94,">0") -> 7 | I94: 0 | J94: 3252.64 | K94: 9841.44 | L94: 5623.68 | M94: 2709.76 | N94: 5238.56 | O94: 8530.64 | P94: 9289.28 | Q94: =SUBTOTAL(109,I94:P94) -> 44486 | R94: 676.28 | S94: =COUNTIF(I94:P94,">0") -> 7 | T94: =Q94-R94 -> 43809.72 | U94: =IF(Q94=0,0,R94/Q94) -> 0.015202086 | V94: {=_xlfn.IFS(S94=0,"Alta sin facturar",S94>2,"Cliente",S94>0,"Cliente nuevo")} -> Cliente | W94: =IF(T94<1,"Sin pago","Ha pagado") -> Ha pagado
A95: 44582 | B95: =PROPER(TEXT(A95,"mmmm")) -> Enero | C95: Christian Castellanos | D95: =VLOOKUP(Datos!$C95,$AQ$2:$AR$41,2,0) -> Norte | E95: 23173 | F95: {=_xlfn.IFS(H95=0,"Alta sin facturar",H95>2,"Cliente",H95>0,"Cliente nuevo")} -> Alta sin facturar | H95: =COUNTIF(I95:P95,">0") -> 0 | I95: 0 | J95: 0 | K95: 0 | L95: 0 | M95: 0 | N95: 0 | O95: 0 | P95: 0 | Q95: =SUBTOTAL(109,I95:P95) -> 0 | S95: =COUNTIF(I95:P95,">0") -> 0 | T95: =Q95-R95 -> 0 | U95: =IF(Q95=0,0,R95/Q95) -> 0 | V95: {=_xlfn.IFS(S95=0,"Alta sin facturar",S95>2,"Cliente",S95>0,"Cliente nuevo")} -> Alta sin facturar | W95: =IF(T95<1,"Sin pago","Ha pagado") -> Sin pago
A96: 44582 | B96: =PROPER(TEXT(A96,"mmmm")) -> Enero | C96: Rubí Rodríguez | D96: =VLOOKUP(Datos!$C96,$AQ$2:$AR$41,2,0) -> Centro | E96: 23174 | F96: {=_xlfn.IFS(H96=0,"Alta sin facturar",H96>2,"Cliente",H96>0,"Cliente nuevo")} -> Cliente | H96: =COUNTIF(I96:P96,">0") -> 5 | I96: 1923.28 | J96: 3056.6 | K96: 0 | L96: 530.12 | M96: 1786.4 | N96: 962.8 | O96: 0 | P96: 0 | Q96: =SUBTOTAL(109,I96:P96) -> 8259.2 | R96: 962.8 | S96: =COUNTIF(I96:P96,">0") -> 5 | T96: =Q96-R96 -> 7296.4 | U96: =IF(Q96=0,0,R96/Q96) -> 0.11657303 | V96: {=_xlfn.IFS(S96=0,"Alta sin facturar",S96>2,"Cliente",S96>0,"Cliente nuevo")} -> Cliente | W96: =IF(T96<1,"Sin pago","Ha pagado") -> Ha pagado
A97: 44582 | B97: =PROPER(TEXT(A97,"mmmm")) -> Enero | C97: Ricardo Vidal | D97: =VLOOKUP(Datos!$C97,$AQ$2:$AR$41,2,0) -> Magallanes | E97: 23175 | F97: {=_xlfn.IFS(H97=0,"Alta sin facturar",H97>2,"Cliente",H97>0,"Cliente nuevo")} -> Cliente nuevo | H97: =COUNTIF(I97:P97,">0") -> 2 | I97: 0 | J97: 1.16 | K97: 0 | L97: 0 | M97: 0 | N97: 2494 | O97: 0 | P97: 0 | Q97: =SUBTOTAL(109,I97:P97) -> 2495.16 | R97: 1682 | S97: =COUNTIF(I97:P97,">0") -> 2 | T97: =Q97-R97 -> 813.16 | U97: =IF(Q97=0,0,R97/Q97) -> 0.67410507 | V97: {=_xlfn.IFS(S97=0,"Alta sin facturar",S97>2,"Cliente",S97>0,"Cliente nuevo")} -> Cliente nuevo | W97: =IF(T97<1,"Sin pago","Ha pagado") -> Ha pagado
A98: 44583 | B98: =PROPER(TEXT(A98,"mmmm")) -> Enero | C98: Genaro Castro | D98: =VLOOKUP(Datos!$C98,$AQ$2:$AR$41,2,0) -> Sur | E98: 23176 | F98: {=_xlfn.IFS(H98=0,"Alta sin facturar",H98>2,"Cliente",H98>0,"Cliente nuevo")} -> Cliente | H98: =COUNTIF(I98:P98,">0") -> 4 | I98: 0 | J98: 0 | K98: 0 | L98: 5175.92 | M98: 2622.76 | N98: 2215.6 | O98: 2680.76 | P98: 0 | Q98: =SUBTOTAL(109,I98:P98) -> 12695.04 | R98: 0 | S98: =COUNTIF(I98:P98,">0") -> 4 | T98: =Q98-R98 -> 12695.04 | U98: =IF(Q98=0,0,R98/Q98) -> 0 | V98: {=_xlfn.IFS(S98=0,"Alta sin facturar",S98>2,"Cliente",S98>0,"Cliente nuevo")} -> Cliente | W98: =IF(T98<1,"Sin pago","Ha pagado") -> Ha pagado
A99: 44583 | B99: =PROPER(TEXT(A99,"mmmm")) -> Enero | C99: Yuriana Argüello | D99: =VLOOKUP(Datos!$C99,$AQ$2:$AR$41,2,0) -> Centro | E99: 23177 | F99: {=_xlfn.IFS(H99=0,"Alta sin facturar",H99>2,"Cliente",H99>0,"Cliente nuevo")} -> Alta sin facturar | H99: =COUNTIF(I99:P99,">0") -> 0 | I99: 0 | J99: 0 | K99: 0 | L99: 0 | M99: 0 | N99: 0 | O99: 0 | P99: 0 | Q99: =SUBTOTAL(109,I99:P99) -> 0 | S99: =COUNTIF(I99:P99,">0") -> 0 | T99: =Q99-R99 -> 0 | U99: =IF(Q99=0,0,R99/Q99) -> 0 | V99: {=_xlfn.IFS(S99=0,"Alta sin facturar",S99>2,"Cliente",S99>0,"Cliente nuevo")} -> Alta sin facturar | W99: =IF(T99<1,"Sin pago","Ha pagado") -> Sin pago
A100: 44585 | B100: =PROPER(TEXT(A100,"mmmm")) -> Enero | C100: Yuritzi Alejo | D100: =VLOOKUP(Datos!$C100,$AQ$2:$AR$41,2,0) -> Centro | E100: 23178 | F100: {=_xlfn.IFS(H100=0,"Alta sin facturar",H100>2,"Cliente",H100>0,"Cliente nuevo")} -> Cliente nuevo | H100: =COUNTIF(I100:P100,">0") -> 1 | I100: 0 | J100: 0 | K100: 0 | L100: 0 | M100: 0 | N100: 0 | O100: 0 | P100: 4721.2 | Q100: =SUBTOTAL(109,I100:P100) -> 4721.2 | R100: 0 | S100: =COUNTIF(I100:P100,">0") -> 1 | T100: =Q100-R100 -> 4721.2 | U100: =IF(Q100=0,0,R100/Q100) -> 0 | V100: {=_xlfn.IFS(S100=0,"Alta sin facturar",S100>2,"Cliente",S100>0,"Cliente nuevo")} -> Cliente nuevo | W100: =IF(T100<1,"Sin pago","Ha pagado") -> Ha pagado
...
